{"author":{"name":"kvl","uri":"https:\/\/kvlrap.wordpress.com"},"title":{"@type":"html","$":"10 (Cehennem Yurdu: Hira)"},"link":[{"@rel":"alternate","@type":"text\/html","@href":"https:\/\/kvlrap.wordpress.com\/2019\/05\/24\/10-cehennem-yurdu-hira\/"},{"@rel":"replies","@type":"text\/html","@href":"https:\/\/kvlrap.wordpress.com\/2019\/05\/24\/10-cehennem-yurdu-hira\/#comments","@thr:count":"1"},{"@rel":"replies","@type":"application\/atom+xml","@href":"https:\/\/kvlrap.wordpress.com\/2019\/05\/24\/10-cehennem-yurdu-hira\/feed\/atom\/","@thr:count":"1"}],"id":"http:\/\/kvlrap.wordpress.com\/?p=942","updated":"2020-04-06T09:40:48Z","published":"2019-05-24T09:25:06Z","category":[{"@scheme":"https:\/\/kvlrap.wordpress.com","@term":"Yaz\u0131lar"},{"@scheme":"https:\/\/kvlrap.wordpress.com","@term":"Cehennem Yurdu: Hira (Roman)"}],"summary":{"@type":"html","$":"10 D\u00fcn gece bir \u015fiir yazd\u0131n imam odas\u0131nda uyumadan evvel. \u0130smine de &#8216;Olacak Olana A\u011f\u0131t&#8216; dedin. \u015eimdi y\u00e2rinle birlikte bir bankta oturuyorsunuz. Yazd\u0131\u011f\u0131n \u015fiirleri ilk ona okutmay\u0131 seviyorsun. Onun \u015fiir okuma kabiliyeti var \u00fcstelik. \u00dcst duda\u011f\u0131n\u0131 inceltip a\u011fz\u0131n\u0131 k\u00fc\u00e7\u00fcc\u00fck a\u00e7arak biraz nefes \u00e7ekiyor i\u00e7ine ve okumaya ba\u015fl\u0131yor: Toprak sinmi\u015f al\u0131n Mahmur bir \u00e7ift g\u00f6z Diz &#8230; <a href=\"https:\/\/kvlrap.wordpress.com\/2019\/05\/24\/10-cehennem-yurdu-hira\/\" class=\"more-link\">Okumaya devam et <span class=\"screen-reader-text\">10 (Cehennem Yurdu:&#160;Hira)<\/span><\/a>"},"content":{"@type":"html","$":"<p style=\"text-align:center;\"><strong>10<br \/>\n<\/strong><\/p>\n<p style=\"text-align:justify;\">D\u00fcn gece bir \u015fiir yazd\u0131n imam odas\u0131nda uyumadan evvel. \u0130smine de &#8216;<em>Olacak Olana A\u011f\u0131t<\/em>&#8216; dedin. \u015eimdi y\u00e2rinle birlikte bir bankta oturuyorsunuz. Yazd\u0131\u011f\u0131n \u015fiirleri ilk ona okutmay\u0131 seviyorsun. Onun \u015fiir okuma kabiliyeti var \u00fcstelik.<\/p>\n<p style=\"text-align:justify;\">\u00dcst duda\u011f\u0131n\u0131 inceltip a\u011fz\u0131n\u0131 k\u00fc\u00e7\u00fcc\u00fck a\u00e7arak biraz nefes \u00e7ekiyor i\u00e7ine ve okumaya ba\u015fl\u0131yor:<\/p>\n<p style=\"text-align:justify;padding-left:30px;\"><em>Toprak sinmi\u015f al\u0131n<br \/>\n<\/em><em>Mahmur bir \u00e7ift g\u00f6z<br \/>\n<\/em><em>Diz kapaklar\u0131nda yara<br \/>\n<\/em><em>Halvet kokan a\u011f\u0131z<br \/>\n<\/em><em>Ve evet!<br \/>\n<\/em><em>G\u00fcne\u015f do\u011far balkonlara<\/em><\/p>\n<p style=\"text-align:justify;padding-left:30px;\"><em>-O-<br \/>\n<\/em><em>Zira ku\u015flar uymaz bu \u00e7a\u011f\u0131n getirdiklerine<br \/>\n<\/em><em>Bu da\u011f\u0131n eteklerinde konaklamaz art\u0131k atlar<br \/>\n<\/em><em>\u00c7ok hayal kurmaz \u00e7illi bir k\u0131z, r\u00fcya g\u00f6rmez<br \/>\n<\/em><em>Belki de \u00f6p\u00fclse kurba\u011fa olacak<\/em><em>\u00a0<\/em><\/p>\n<p style=\"text-align:justify;padding-left:30px;\"><em>Peki ne yapar bu<br \/>\n<\/em><em>Hi\u00e7 mi bir ku\u015fa boyun e\u011fmez tay<br \/>\n<\/em><em>Hi\u00e7 mi koymaz \u00e7enesine di\u015fi avu\u00e7lar\u0131n\u0131, ah<br \/>\n<\/em><em>Grevlere de kat\u0131lmaz<br \/>\n<\/em><em>Yetecek midir g\u00f6rd\u00fckleri hayat\u0131 boyunca<br \/>\n<\/em><em>o \u0131ss\u0131z dubalarda<\/em><\/p>\n<p style=\"text-align:justify;padding-left:30px;\"><em>Bir at\u2019\u0131n \u00f6zlemidir belki de i\u00e7indeki<br \/>\n<\/em><em>Bir \u00e7\u0131rp\u0131da \u00e7\u0131rp\u0131lan kanatla kat edilen da\u011flar\u0131n.<br \/>\n<\/em><em>Ya\u015fad\u0131\u011f\u0131n\u0131n sa\u011flamas\u0131n\u0131 yapamay\u0131\u015f\u0131n<br \/>\n<\/em><em>tezcanl\u0131l\u0131\u011f\u0131yla s\u00fcr\u00fcklenmi\u015f<br \/>\n<\/em><em>Baudelaire ile Bedreddin\u2019in aras\u0131nda.<\/em><\/p>\n<p style=\"text-align:justify;padding-left:30px;\"><em>Sokaklar\u0131 k\u0131rg\u0131nl\u0131kla ar\u015f\u0131nlam\u0131\u015f<br \/>\n<\/em><em>En uygun ad\u0131m mar\u015flarla t\u0131p\u0131\u015f t\u0131p\u0131\u015f<br \/>\n<\/em><em>Bilyeler ve bilhassa \u00e7atapatlarla<br \/>\n<\/em><em>De\u011fi\u015f toku\u015f ederlerken hayatlar\u0131n\u0131 arkada\u015flarla<\/em><\/p>\n<p style=\"text-align:justify;padding-left:30px;\"><em>Herkes bir r\u00fcya g\u00f6r\u00fcyor<br \/>\n<\/em><em>Herkes r\u00fcyas\u0131nda dalm\u0131\u015f<br \/>\n<\/em><em>Oysa o ise.<br \/>\n<\/em><em>Ona ba\u015fkalar\u0131n\u0131n r\u00fcyalar\u0131 kalm\u0131\u015f<br \/>\n<\/em><em>Herkes bir r\u00fcya g\u00f6r\u00fcyor<br \/>\n<\/em><em>Ona kalan r\u00fcyalarda yang\u0131n<br \/>\n<\/em><em>Oysa o ise.<br \/>\n<\/em><em>Bir denizin en dibine de\u011fmi\u015f<br \/>\n<\/em><em>Herkes bir r\u00fcya g\u00f6r\u00fcyor<br \/>\n<\/em><em>Hi\u00e7 olmam\u0131\u015f kendi r\u00fcyas\u0131<br \/>\n<\/em><em>Tutu\u015ftu\u011fu yerden tutunmu\u015f<br \/>\n<\/em><em>Ba\u015fka r\u00fcyalarda<\/em><\/p>\n<p style=\"text-align:justify;padding-left:30px;\"><em>Ac\u0131n\u0131n taraf\u0131nda olmak.<br \/>\n<\/em><em>Yar\u0131n\u0131n araf\u0131nda bir ku\u015fun kanad\u0131nda do\u011fmak<br \/>\n<\/em><em>Bir su\u00e7un k\u0131y\u0131s\u0131ndan<br \/>\n<\/em><em>Bir yolun yar\u0131s\u0131ndan d\u00f6nmek<br \/>\n<\/em><em>Bir sonun en ba\u015f\u0131ndan.<br \/>\n<\/em><em>\u00dc\u00e7 gece tam, Allah&#8217;\u0131n kap\u0131s\u0131nda yatmak<br \/>\n<\/em><em>Soka\u011f\u0131ndaki k\u00f6peklere az\u0131\u011f\u0131ndan b\u00f6lmek<br \/>\n<\/em><em>Suyuna t\u00fck\u00fcrd\u00fc\u011f\u00fcn vahay\u0131 uykulu g\u00f6zler ve<br \/>\n<\/em><em>kupkuru bir a\u011f\u0131zla yal\u0131nayak terk etmek<br \/>\n<\/em><em>En mahzun sath\u0131yd\u0131 bu \u00e7a\u011f\u0131n<\/em><\/p>\n<p style=\"text-align:justify;padding-left:30px;\"><em>-Sen-<br \/>\n<\/em><em>Terk etmek ve yola koyulmak.<br \/>\n<\/em><em>Kalaca\u011f\u0131n da\u011f\u0131 se\u00e7mek pek me\u015fakkatli olmamal\u0131<br \/>\n<\/em><em>\u0130ndi\u011finde bulaca\u011f\u0131n kasaba hi\u00e7 de\u011fi\u015fmemi\u015f olacak<br \/>\n<\/em><em>Bilindik bir ezan ve ez\u00e2 hali<br \/>\n<\/em><em>En h\u00fcz\u00fcnl\u00fc \u015fekilde d\u00fc\u015fecek g\u00f6nl\u00fcne sal\u00e2t vakti<\/em><\/p>\n<p style=\"text-align:justify;padding-left:30px;\"><em>Fakat asla \u00f6zsavunma olarak \u2018d\u00fc\u015f\u00fcnecek\u2019mi\u015f<br \/>\n<\/em><em>gibi bakma onlara<br \/>\n<\/em><em>Z\u0131t tutarlar seni, \u00f6fkeli ve fakat g\u00fc\u00e7s\u00fcz derler<br \/>\n<\/em><em>sevgisiz ve zorba sesleriyle.<br \/>\n<\/em><em>Sen bakma onlara<br \/>\n<\/em><em>Onlar hat\u0131rs\u0131z hat\u0131ras\u0131z kalm\u0131\u015f<\/em><\/p>\n<p style=\"text-align:justify;padding-left:30px;\"><em>Herkes bir r\u00fcya g\u00f6r\u00fcyor<br \/>\n<\/em><em>Herkes r\u00fcyas\u0131nda dalm\u0131\u015f<br \/>\n<\/em><em>Herkes bir r\u00fcya g\u00f6r\u00fcyor<br \/>\n<\/em><em>D\u00fcnya r\u00fcyalarda kalm\u0131\u015f<br \/>\n<\/em><em>Herkes bir r\u00fcya g\u00f6r\u00fcyor<br \/>\n<\/em><em>Kimse g\u00f6r\u00fcnmek istemiyor \/ Sense.<br \/>\n<\/em><em>B\u0131rak\u0131p bunlar\u0131 bu falanlar\u0131 filanlar\u0131<br \/>\n<\/em><em>Y\u00fcr\u00fcm\u00fc\u015f y\u00fcr\u00fcm\u00fc\u015f bir g\u00fcne\u015fe varm\u0131\u015fs\u0131n<br \/>\n<\/em><em>\u00c7ok ama \u00e7ok tehlikeli bir i\u015f yapm\u0131\u015f<br \/>\n<\/em><em>Herkes bir r\u00fcya g\u00f6r\u00fcyorken sen<br \/>\n<\/em><em>Birinin r\u00fcyas\u0131na girmi\u015fsin<\/em><\/p>\n<p style=\"text-align:justify;padding-left:30px;\"><em>Ah \u015fimdi o ku\u015f on d\u00f6rd\u00fcnc\u00fc kata \u00e7arpar \u00f6l\u00fcr<br \/>\n<\/em><em>Ve o tay \u00fc\u00e7 gecede b\u00fcy\u00fcr \u00fc\u00e7 kurda yem olur<br \/>\n<\/em><em>Zaten o okulda \u00e7al\u0131\u015fsan da yapamayacaks\u0131n matemati\u011fi,<br \/>\n<\/em><em>Benim hayat\u0131m \u015fiir olmu\u015f deyip edebiyat\u0131<br \/>\n<\/em><em>Ve tam da b\u00f6yle bir gecede baban \u00f6lm\u00fc\u015f<br \/>\n<\/em><em>Bankalar vurmu\u015f onu<br \/>\n<\/em><em>Aln\u0131n\u0131n dibinden.<br \/>\n<\/em><em>Zaten sen de \u00f6ld\u00fcn<br \/>\n<\/em><em>Benim hayat\u0131m \u015fiir olmu\u015f derken.<\/em><\/p>\n<p style=\"text-align:justify;padding-left:30px;\"><em>Adam uyanm\u0131\u015f r\u00fcyadan, r\u00fcya dalm\u0131\u015f uykuya<br \/>\n<\/em><em>Ta ki sen do\u011fana dek<br \/>\n<\/em><em>Do\u011fan do\u011furur<br \/>\n<\/em><em>\u00c7o\u011falan \u00e7ocuktur<br \/>\n<\/em><em>Yoldad\u0131r seyirdedir<br \/>\n<\/em><em>\u00c7a\u011f\u0131ldar olur \u00f6l\u00fcr<br \/>\n<\/em><em>Sen merak etme, r\u00fcya seni g\u00f6r\u00fcr<br \/>\n<\/em><em>Sen merak etme, \u00f6l\u00fcm seni bulur<br \/>\n<\/em><em>Merak etme<br \/>\n<\/em><em>Olan \u00f6l\u00fcr \u00f6len olur<\/em><em>\u00a0<\/em><\/p>\n<p style=\"text-align:justify;padding-left:30px;\"><em>-Biz-<br \/>\n<\/em><em>Al\u00e2k dedi g\u00fczel kokulu adam<br \/>\n<\/em><em>Al\u00e2k dedi bildin<br \/>\n<\/em><em>Bir t\u00fcl\u00fcn ard\u0131ndaki dibdiri s\u0131rr\u0131<br \/>\n<\/em><em>Sen kime al\u00e2ks\u0131n, biz kime?<br \/>\n<\/em><em>\u015eu da\u011f\u0131n kalbi at\u0131yordu duydun<br \/>\n<\/em><em>Kard\u0131\u011f\u0131n harc\u0131n nefesi kristalleniyordu so\u011fuktan<br \/>\n<\/em><em>Tel\u00e2\u015f\u0131ndan kar\u015f\u0131 koyam\u0131yordu a\u011fa\u00e7, baltas\u0131na, tel\u00e2\u015f\u0131ndan<br \/>\n<\/em><em>Bir at sohbet etti bir ku\u015fla<\/em><\/p>\n<p style=\"text-align:justify;padding-left:30px;\"><em>Marifetin bu mudur al\u00e2k?<br \/>\n<\/em><em>Da\u011flara tutulmu\u015f g\u00f6nl\u00fcn d\u00f6n\u00fc\u015f\u00fc olur mu?<br \/>\n<\/em><em>Cami ile mezarl\u0131k mesafesidir hayat<br \/>\n<\/em><em>\u0130\u015fte, seninle temizlendi \u015fu \u0131rmak<br \/>\n<\/em><em>Seninle b\u00fckl\u00fcm b\u00fckl\u00fcm oldu \u00e7i\u00e7ekler<br \/>\n<\/em><em>Geyikler seninle susuzlu\u011funu giderdi<br \/>\n<\/em><em>Senin i\u00e7in topland\u0131 kitap, \u00e7a\u011flad\u0131 derya<br \/>\n<\/em><em>Sen her gitti\u011finde secdeye<br \/>\n<\/em><em>Seccaden de y\u00fcz\u00fcn\u00fc koyacak yer arard\u0131<br \/>\n<\/em><em>Ya\u011fmurlar ya\u011facak bir yer arard\u0131 g\u00f6nl\u00fcnde<br \/>\n<\/em><em>Akl\u0131n ne zaman bir yere tak\u0131lsa<br \/>\n<\/em><em>Ve hep buluverirlerdi o yemye\u015fil koruyu.<br \/>\n<\/em><em>Ve kap\u0131n her \u00e7almaktan \u00f6nceleri<br \/>\n<\/em><em>Ku\u015fa\u011f\u0131n\u0131 b\u00fcr\u00fcn\u00fcr<br \/>\n<\/em><em>Zillerini s\u00fcr\u00fcn\u00fcrd\u00fc<br \/>\n<\/em><em>Ve sen saatine her bakt\u0131\u011f\u0131nda<br \/>\n<\/em><em>Vakit tamamd\u0131.<br \/>\n<\/em><em>Cami ile mezarl\u0131k mesafesidir hayat<br \/>\n<\/em><em>Seni orada bulacaklar<br \/>\n<\/em><em>Orada g\u00f6r\u00fclecek hesap<br \/>\n<\/em><em>Seninle bir olacak yer, yerle bir olacak \u015fehir<\/em><\/p>\n<p style=\"text-align:justify;padding-left:30px;\"><em>\u00c7\u00fcnk\u00fc vard\u0131n derya dibindeki o k\u0131z\u0131l vicdana<br \/>\n<\/em><em>Olacak olan oldu da\u011f oldu \u00e7i\u00e7ek oldu<br \/>\n<\/em><em>Omuzlarda ta\u015f\u0131n\u0131lan kallavi tabutlar<br \/>\n<\/em><em>Oldu i\u015fte oldu y\u00fcre\u011finden d\u00fc\u015ft\u00fc bir \u00e7i\u011f titredin<\/em><\/p>\n<p style=\"text-align:justify;padding-left:30px;\"><em>Herkes bir r\u00fcya g\u00f6r\u00fcyor<br \/>\n<\/em><em>Herkes r\u00fcyas\u0131nda dalm\u0131\u015f<br \/>\n<\/em><em>Herkes bir r\u00fcya g\u00f6r\u00fcyor<br \/>\n<\/em><em>Hakiyk\u00e2tten kopmu\u015f<br \/>\n<\/em><em>Herkes bir r\u00fcya g\u00f6r\u00fcyor<br \/>\n<\/em><em>Ger\u00e7eklerden farks\u0131z<br \/>\n<\/em><em>Herkes bir r\u00fcya g\u00f6r\u00fcyor<br \/>\n<\/em><em>\u00d6tekini duymak istemiyor<br \/>\n<\/em><em>Bir r\u00fcya g\u00f6r\u00fcyor herkes<br \/>\n<\/em><em>Bir r\u00fcya g\u00f6r\u00fcyor<br \/>\n<\/em><em>Oysa o ise.<br \/>\n<\/em><em>Varm\u0131\u015f bir ba\u015fkas\u0131n\u0131n r\u00fcyas\u0131na dalm\u0131\u015f<br \/>\n<\/em><em>G\u00f6r\u00fcp g\u00f6rece\u011fi daha ne varm\u0131\u015f<\/em><\/p>\n<p style=\"text-align:justify;padding-left:30px;\"><em>Allah\u2019\u0131ndan bulmu\u015f b\u00fct\u00fcn o peygamberler<br \/>\n<\/em><em>Tartaklanm\u0131\u015f ya\u011fmalanm\u0131\u015f canh\u0131ra\u015f melekler<br \/>\n<\/em><em>Kalbi h\u00e2l\u00e2 atmakta olan kitaplar<br \/>\n<\/em><em>Ve insan,<br \/>\n<\/em><em>\u00c7\u00fcr\u00fck\u00e7\u00fcl bir ku\u015f kadar g\u00fczel<br \/>\n<\/em><em>Bir o kadar ta\u00e7yapraklar ok\u015farken onu<br \/>\n<\/em><em>Ne s\u00f6yleyebilir ki bu masum k\u0131z \u00f6l\u00fcrse.<\/em><\/p>\n<p style=\"text-align:justify;padding-left:30px;\"><em>S\u00f6yler<br \/>\n<\/em><em>Bir a\u011f\u0131t bir muhakeme bir yurt kurar<br \/>\n<\/em><em>Sinesinde T\u00fbr-i Sina<br \/>\n<\/em><em>Avucunda s\u0131ms\u0131k\u0131 bir y\u00fcrekle<br \/>\n<\/em><em>Z\u00fclf\u00fcn\u00fc de\u011fdirmeden zulme<br \/>\n<\/em><em>Se\u011firmeden g\u00f6zleri<br \/>\n<\/em><em>Elbette ta\u015f\u0131n ba\u011fr\u0131n\u0131 yarar,<br \/>\n<\/em><em>Kar\u0131nca yuvalar\u0131 gibi.<\/em><\/p>\n<p style=\"text-align:justify;padding-left:30px;\"><em>Ey halk y\u0131\u011f\u0131nlar\u0131<br \/>\n<\/em><em>Ey mesk\u00fbn mahaller<br \/>\n<\/em><em>Ey hanlar haneler hanedanlar<br \/>\n<\/em><em>K\u0131z\u0131n ge\u00e7ti\u011fi halklar -H\u00eere\u2019den Hira\u2019ya-<br \/>\n<\/em><em>Eskiden daha yaln\u0131zs\u0131z daha yoksuzmu\u015f<br \/>\n<\/em><em>Ya ona s\u0131k\u0131l\u0131r can\u0131<br \/>\n<\/em><em>Bilyeler ve ku\u015flar ve r\u00fcya<br \/>\n<\/em><em>ve bir t\u00fcrl\u00fc g\u00f6remedi\u011fi at<br \/>\n<\/em><em>Sizden daha k\u0131ymetli<br \/>\n<\/em><em>G\u00f6ze g\u00f6z<br \/>\n<\/em><em>Di\u015fe di\u015f \u00e7atapat<br \/>\n<\/em><em>Hayat<\/em><\/p>\n<p style=\"text-align:justify;\">&#8220;\u00c7ok g\u00fczel,&#8221; diye inleyiveriyor y\u00e2rin okumay\u0131 bitirdi\u011fi anda. &#8220;\u00c7ok ho\u015f olmu\u015f bu.&#8221; Bir s\u00fcre bekledikten sonra, &#8220;Sende,&#8221; diyor, &#8220;da\u011f ve at \u00f6zlemi mi var?&#8221;<\/p>\n<p style=\"text-align:justify;\">&#8220;Olabilir,&#8221; diyorsun, &#8220;sonu\u00e7ta bir \u015fiir bu. Fakat &#8216;vakan\u00fcvis&#8217; ad\u0131yla \u00fcretti\u011fim t\u00fcrde bir \u015fiir oldu\u011fu i\u00e7in orada yaz\u0131lanlar\u0131n birebir bende olmas\u0131 gerekmiyor.&#8221;<\/p>\n<p style=\"text-align:justify;\">&#8220;Vakan\u00fcvis nedir?&#8221;<\/p>\n<p style=\"text-align:justify;\">&#8220;Osmanl\u0131 zaman\u0131nda olaylar\u0131 yazan defterdarlard\u0131r vakan\u00fcvisler. Buradan yola \u00e7\u0131karak, e\u011fer bir \u015fiirde do\u011frudan kendimi, i\u00e7inde bulundu\u011fum vaziyeti filan anlatmay\u0131p, ba\u015fka bir karakter yarat\u0131p ve bir durumdan yola \u00e7\u0131karak bir olay kurgulay\u0131p onun \u015fiirini yazarsam buna &#8216;vakan\u00fcvis&#8217; tarz\u0131 diyorum.&#8221;<\/p>\n<p style=\"text-align:justify;\">&#8220;Anlad\u0131m ama zaten b\u00fct\u00fcn \u015fairler bunu yap\u0131yor a\u015fa\u011f\u0131 yukar\u0131. \u015eairlerin yalanc\u0131l\u0131klar\u0131 da buradan gelmiyor mu zaten? Ya\u015famad\u0131\u011f\u0131 bir durumu ya\u015fam\u0131\u015f gibi anlat\u0131yor.&#8221;<\/p>\n<p style=\"text-align:justify;\">&#8220;Do\u011fru. Fakat bu durum daha farkl\u0131. Bahsetti\u011fin \u015fairler ya\u015famad\u0131\u011f\u0131n\u0131 ya\u015fam\u0131\u015f gibi anlat\u0131r. Ben ise ya\u015famada\u011f\u0131m\u0131 ya\u015fayan\u0131n ya\u015fad\u0131\u011f\u0131 \u015fekilde anlat\u0131yorum.&#8221;<\/p>\n<p style=\"text-align:justify;\">&#8220;\u015eimdi oldu.&#8221;<\/p>\n<p style=\"text-align:justify;\">&#8220;Bahsetti\u011fin yalanc\u0131 \u015fairler Kur&#8217;an&#8217;da ele\u015ftiriliyor, biliyor musun? \u015euara, yani \u015fairler s\u00fbresinde birden \u015fairlere \u00e7at\u0131yor. \u015eairlerin arkas\u0131na sapk\u0131nlar\u0131n d\u00fc\u015ft\u00fc\u011f\u00fcn\u00fc, onlar\u0131n vadilerde \u015fa\u015fk\u0131n \u015fa\u015fk\u0131n dola\u015ft\u0131klar\u0131n\u0131 ve asla yapamayacaklar\u0131 \u015feyler s\u00f6ylediklerini anlat\u0131yor. Bunu okudu\u011fumda \u00fcrkm\u00fc\u015ft\u00fcm. Fakat sonra hemen bir istisnadan bahsediyor \u015fairlerin aras\u0131nda, &#8216;Ancak iman edip iyilik, g\u00fczellik, do\u011fruluk i\u00e7in \u00e7al\u0131\u015fanlar, Allah&#8217;\u0131 \u00e7ok\u00e7a ananlar ve zulme u\u011frad\u0131ktan sonra kendilerini savunanlar ba\u015fka&#8217; diyerek.&#8221;<\/p>\n<p style=\"text-align:justify;\">&#8220;\u00c7ok g\u00fczel. \u0130yilik, g\u00fczellik, do\u011fruluk i\u00e7in \u00e7al\u0131\u015fan \u00e7ok daha fazla \u015faire gerek var.&#8221;<\/p>\n<p style=\"text-align:justify;\">&#8220;Bence daha fazla \u015faire gerek yok. Her \u015feyin az\u0131 ve \u00f6z\u00fc iyi. \u0130sl\u00e2m&#8217;a \u00fc\u00e7 be\u015f ki\u015fi az girseydi \u015fu an bar\u0131\u015f i\u00e7inde ya\u015fayan bir kom\u00fcn olacaklard\u0131. \u0130nsanlar g\u00f6\u00e7ebelikten yerle\u015fik hayata ge\u00e7meseydi \u00e7ok daha bar\u0131\u015f\u00e7\u0131l bir d\u00fcnya olacakt\u0131. Sosyolojik ara\u015ft\u0131rmaya g\u00f6re bir topluluk altm\u0131\u015f ki\u015fiyi ge\u00e7erse yozla\u015fma ba\u015flar.&#8221;<\/p>\n<p style=\"text-align:justify;\">&#8220;O zaman elli sekizden az \u00e7ocuk yapmaya dikkat ederiz.&#8221; Bir kahkaha patlat\u0131yorsun.<\/p>\n<p style=\"text-align:justify;\">&#8220;Kahrolas\u0131 beyhude sosyoloji!&#8221; diyorsun sevin\u00e7le.<\/p>\n<p style=\"text-align:justify;\">&#8220;Yozla\u015fmam\u0131z\u0131 asla istemem. Duydun mu beni? Sen buraya gelmeden evvel seni ne kadar \u00f6zledi\u011fimi d\u00fc\u015f\u00fcn\u00fcyordum. Epeyi \u00fcz\u00fclm\u00fc\u015ft\u00fcm. Ama birden \u00f6n\u00fcmde y\u00fcr\u00fcyen kamburlu bir adam g\u00f6rd\u00fcm. K\u0131sa boylu, bir omzu yukar\u0131da, kambur ve a\u011f\u0131r aksak y\u00fcr\u00fcyen bir adamd\u0131. Hi\u00e7 olmad\u0131\u011f\u0131m \u015fekilde pi\u015fman oldum. Yani, sen okulundas\u0131n, ben okulumday\u0131m, sa\u011fl\u0131\u011f\u0131m\u0131z s\u0131hhatimiz yerinde. \u0130nternetten de g\u00f6r\u00fc\u015febiliyoruz. Bu durumda kalk\u0131p \u00f6zledim diyerek isyan eder gibi oluyorum! Ne kadar bo\u015f bir s\u0131k\u0131nt\u0131d\u0131r bu o adam kar\u015f\u0131s\u0131nda? Nas\u0131l da m\u0131zm\u0131zlanmaya ve nank\u00f6rl\u00fc\u011fe meyilli yarat\u0131klar\u0131z. \u00d6yle de\u011fil mi?&#8221;<\/p>\n<p style=\"text-align:justify;\">&#8220;\u00c7ok hakl\u0131s\u0131n. Sen \u00e7ok vefal\u0131 birisin&#8221; diyorsun. Bir yandan da y\u00e2rinin bu s\u00f6zlerinden akl\u0131na bir dize d\u00fc\u015f\u00fcyor: &#8220;<em>Seni sevemiyorum \u00e7\u00fcnk\u00fc&#8230; ya\u015famak istiyorum.<\/em>&#8220;<\/p>\n<p style=\"text-align:justify;\">&#8220;Olmas\u0131 gereken bu. \u0130sim takmaya l\u00fczum yok,&#8221; diyor y\u00e2rin. &#8220;\u0130lk f\u0131rsatta s\u0131hhati yerinde olmayan ve \u00f6ks\u00fcz ya da yetim \u00e7ocuklara yard\u0131m edece\u011fim. Bunu kendime misyon edindim. Bir \u015fey soraca\u011f\u0131m?&#8221;<\/p>\n<p style=\"text-align:justify;\">&#8220;Buyur.&#8221;<\/p>\n<p style=\"text-align:justify;\">&#8220;Bu zengin insanlar, banka hesaplar\u0131 a\u011f\u0131zlar\u0131na kadar parayla dolu olan insanlar ne yap\u0131yor? Yani ne oluyor da bu muhta\u00e7 insanlar\u0131 g\u00f6rm\u00fcyorlar? Keyifle oturuyorlar koltuklar\u0131nda. Ya, o koltu\u011fu sat\u0131p bir \u015feyler yapar\u0131m. Sonra da yerde otururum. Ne var? Hi\u00e7bir \u015fey kaybetmem. Fakat o muhta\u00e7 ki\u015fi bir hayat, bir evl\u00e2t, bir anne-baba kazan\u0131r.&#8221; \u00d6fkeyle ve h\u0131zla konu\u015fuyordu y\u00e2rin. Kur&#8217;an&#8217;daki \u00f6fkeyi g\u00f6rd\u00fcn onun g\u00f6zlerinde. Anlamveremez ve \u00e7\u00f6z\u00fcm odakl\u0131 bir \u00f6fke. Kur&#8217;an, geceyi a\u00e7 ge\u00e7irenlerin, borca muhta\u00e7 ettirilenlerin, yoksunluk \u00e7ekenlerin \u00f6fkesiyle dolu bir kitap.<\/p>\n<p style=\"text-align:justify;\">&#8220;O zenginlerin hesaplar\u0131ndaki paralarla ne yapt\u0131klar\u0131n\u0131 sormu\u015ftun. Yapt\u0131klar\u0131 \u015fu: O paralar\u0131n faizlerini yiyorlar. O faizi ise krediler ve kredi kartlar\u0131yla bor\u00e7land\u0131r\u0131lan halktan al\u0131yorlar. Yani hem oturduklar\u0131 yerden para kazan\u0131yorlar hem bunu paran\u0131n \u00fczerinden yap\u0131yorlar hem de t\u00fcm bu paray\u0131 muhta\u00e7 olandan al\u0131yorlar.&#8221;<\/p>\n<p style=\"text-align:justify;\">\u00d6fkeyle y\u00fcz\u00fcne bak\u0131yor y\u00e2rin. Kur&#8217;an&#8217;\u0131n \u00f6fkesi bu. Fakat \u00e2yet gibi, bir s\u00fcre bunun \u00fczerinde konu\u015ftuktan sonra s\u0131ra cennet \u00e2yetlerine geliyor. Ne\u015feyle c\u0131v\u0131ld\u0131yor y\u00e2rin:<\/p>\n<p style=\"text-align:justify;\">&#8220;Hadi, kimsenin bizi duyamayaca\u011f\u0131 bir yere gidelim. Sana biraz keman \u00e7almak istiyorum.&#8221;<\/p>\n<p style=\"text-align:justify;\">Kalk\u0131p uzakla\u015f\u0131yorsunuz merkezden. Arkalardaki bir parka do\u011fru ilerliyorsunuz, ge\u00e7en g\u00fcn hotelden ald\u0131\u011f\u0131n s\u0131rt \u00e7antanla ve keman \u00e7antas\u0131yla birlikte. Hava \u0131s\u0131nm\u0131\u015f durumda. Her apartman\u0131n alt\u0131nda market olan bir sokaktan ge\u00e7iyorsunuz. Y\u00e2rin sen yokken buradaki camiye namaz k\u0131lmaya ve parka hava almaya geliyor. Yurda uzak de\u011fil.<\/p>\n<p style=\"text-align:justify;\">Kendinize bir bank se\u00e7ip oturuyorsunuz. Y\u00e2rin \u00e7antadan keman\u0131n\u0131 \u00e7\u0131kar\u0131p akordunu ayarl\u0131yor. Boynuna yerle\u015ftirerek ilk \u00f6\u011frendi\u011fi besteyi \u00e7almaya ba\u015fl\u0131yor. Merakla dinliyorsun.<\/p>\n<p style=\"text-align:justify;\">Bile\u011finin ince esteti\u011fi ve kolunun nazik kuvvetiyle ba\u015fl\u0131yor t\u0131\u011f, bir k\u0131l\u0131\u00e7 gibi duran ar\u015feyi keman\u0131n tellerine s\u00fcrtmeye. Baz\u0131 k\u0131s\u0131mlarda suyun alt\u0131ndaym\u0131\u015f gibi a\u011f\u0131rla\u015fan hareketler bazen de \u00e2nile\u015ferek keman tellerinden ahenkli sesler \u00e7\u0131kar\u0131yor. Notalar birle\u015ferek melodiyi tamaml\u0131yor. Bu besteyi biliyorsun. <em>Gurbette \u00d6mr\u00fcm Ge\u00e7ecek<\/em>. Kocaman g\u00fcl\u00fcms\u00fcyorsun. \u00c7\u00fcnk\u00fc bir y\u0131ld\u0131r keman e\u011fitimi alan ve fakat sana hi\u00e7bir \u015fey t\u0131ng\u0131rdatmayan y\u00e2rin senin en sevdi\u011fin \u015fark\u0131lardan biri \u00fczerinde \u00e7al\u0131\u015f\u0131yormu\u015f. Keman hocas\u0131n\u0131n, &#8220;Ben keman tutu\u015funu alt\u0131 ayda \u00f6\u011frendim&#8221; demesine ra\u011fmen o bir y\u0131lda bu besteyi \u00e7alabilecek noktaya gelmi\u015f. Gururlan\u0131yorsun. Gururun tek iyi manas\u0131yla gururlan\u0131yorsun. Koltuklar\u0131n kabar\u0131yor, g\u00f6\u011fs\u00fcn \u015fi\u015fiyor, hayran oluyorsun. Senin yapt\u0131\u011f\u0131n s\u00fcrprizi dahi kar\u015f\u0131l\u0131ks\u0131z b\u0131rakmay\u0131p ertesi g\u00fcn sana s\u00fcrprizlerin en g\u00fczel melodili olan\u0131n\u0131 yapan ve bunda \u00e7ok yetenekli oldu\u011funu ispatlayan bu k\u0131z sana en \u015firin mutluluklar\u0131 ve en hakl\u0131 gururlar\u0131 ya\u015fat\u0131yor.<\/p>\n<p style=\"text-align:justify;\">Birka\u00e7 yerde ritmi biraz \u015fa\u015f\u0131rarak daha da \u015firinlik ekliyor \u015fu anki h\u00e2linize. Fakat bu \u015fa\u015f\u0131rmalar acemili\u011finden de\u011fil, onun melodisine biraz komik bir sesle \u015fark\u0131n\u0131n s\u00f6zlerini m\u0131r\u0131ldanmandan dolay\u0131 kendini tutamay\u0131p sana g\u00fclmesinden kaynaklan\u0131yor. Bu y\u00fczden de en \u015firin hatalar bunlar.<\/p>\n<p style=\"text-align:justify;\">Daha bir sevin\u00e7le \u015fark\u0131y\u0131 s\u00f6yl\u00fcyorsun ve o da \u00e7almaya devam ediyor. Biraz uzaktan da olsa ge\u00e7en herkes size bak\u0131yor. Erkek arkada\u015f\u0131na parkta bir t\u00fcrk\u00fcy\u00fc kemanla \u00e7alan bir k\u0131za \u015fa\u015fk\u0131nl\u0131kla bak\u0131yorlar. A\u015fkl\u0131 olmay\u0131 anlam\u0131yorlar ve o g\u00fcn muktedirin s\u00f6yledi\u011fi s\u00f6zler ba\u011flam\u0131nda bu durumu kendi aralar\u0131nda de\u011ferlendiriyorlar. E\u011flenceli ve fakat yersiz bulanlar da oluyor. Daha acayibi, ge\u00e7en herkes kendisini yorum yapmak zorunda hissediyor.<\/p>\n<p style=\"text-align:justify;\">Bu \u015fahane keman dinletisi bittikten sonra keman\u0131 elinden alarak s\u0131ms\u0131k\u0131 sar\u0131l\u0131yorsun y\u00e2rine. \u00c7ok te\u015fekk\u00fcr ediyorsun ve onu kutluyorsun.<\/p>\n<p style=\"text-align:justify;\">&#8220;Daha tam haz\u0131r de\u011fildim asl\u0131nda,&#8221; diyor y\u00e2rin. &#8220;Bir bu\u00e7uk ay vard\u0131 en az\u0131ndan haz\u0131r olmama. Ama sen erkenden gelince ben de sana s\u00fcrpriz yapabilmek i\u00e7in daha \u00e7ok \u00e7al\u0131\u015ft\u0131m ve ba\u015fard\u0131\u011f\u0131ma inan\u0131yorum. Ama ben biraz acemiyim, do\u011fal olarak.&#8221;<\/p>\n<p style=\"text-align:justify;\">&#8220;Ben de b\u00f6yle sana meftun bir mecnunam&#8230;&#8221;<\/p>\n<p style=\"text-align:justify;\">Cebinde \u00e7ok az bir para var. Hesaplad\u0131\u011f\u0131n gibi gitmedi baz\u0131 \u015feyler. Bug\u00fcn devletten ald\u0131\u011f\u0131n e\u011fitim kredisinin yatmas\u0131 gerekiyordu fakat h\u00e2l\u00e2 yatmad\u0131. Bu sebepten dolay\u0131 \u00e7ok az bir para kald\u0131 ceplerinde. Bankay\u0131 aramay\u0131 d\u00fc\u015f\u00fcn\u00fcyorsun fakat ge\u00e7 oldu. Yar\u0131n sabah arayabilirsin.<\/p>\n<p style=\"text-align:justify;\">Devletin, bir k\u0131sm\u0131n\u0131 \u00f6zelle\u015ftirdi\u011fi bir bankadan al\u0131yorsun her ay e\u011fitim kredisini. Bu bankan\u0131n kart\u0131 var bir de cebinde. Paray\u0131 buraya yat\u0131r\u0131yorlar. Banka kart\u0131n\u0131n yan\u0131nda kredi kart\u0131 da verdiler fakat sen ertesi g\u00fcn gidip bu kredi kart\u0131n\u0131 iptal ettirdin. E\u011fer d\u00fc\u015f\u00fck faizli bir kredi kart\u0131n\u0131 bile reddedersen ileride bankalar aras\u0131ndaki notunun d\u00fc\u015fece\u011fini ve istesen de kart yahut kredi alamayaca\u011f\u0131n\u0131 s\u00f6ylediler. Bunun bir e\u015fk\u0131yal\u0131k oldu\u011funu s\u00f6yledin onlara. Beni komple silebilirsiniz o defterlerden, ben sadece e\u011fitim kredisini alaca\u011f\u0131m dedin. E\u011fer biraz daha \u0131srar etseydiler, anlamayacaklar\u0131 halde onlara \u0130mam-\u0131 Azam&#8217;\u0131n faiz hakk\u0131ndaki hik\u00e2yesini de anlatacakt\u0131n.<\/p>\n<p style=\"text-align:justify;\">\u015eimdi imam odas\u0131ndas\u0131n. Telefonundan e-postan\u0131 kontrol ediyorsun. Yeni bir posta daha gelmi\u015f:<\/p>\n<p style=\"text-align:justify;padding-left:30px;\">Cuma g\u00fcn\u00fc 18 saat \u00e7al\u0131\u015ft\u0131m saniyede 0,0014 TL kazanmak i\u00e7in de\u011fer mi lan 18 saat it gibi \u00e7al\u0131\u015f ald\u0131\u011f\u0131m paraya bak bu y\u00fczden para laz\u0131m diyorum para kazanmaya zaman harcamamal\u0131y\u0131z yok mu bu i\u015fin k\u0131sa bir yolu acaba ya da ne zaman fark edece\u011fiz o k\u0131sa yolu? Tabii bilemiyoruz. 18 saat \u00e7al\u0131\u015f\u0131nca d\u00fcn yerimden kalkamad\u0131m ba\u015f\u0131m falan d\u00f6nd\u00fc\u011f\u00fc i\u00e7in herhangi bir \u015fey yapmam m\u00fcmk\u00fcn olmad\u0131 ak\u015fama do\u011fru falan ge\u00e7ti oturdum et kestim 10 kilo falan kesmi\u015fimdir ba\u015flay\u0131nca b\u0131rak\u0131lam\u0131yor. Yok be karde\u015fim internetin ya\u015f ortalamas\u0131 \u00e7ok d\u00fc\u015ft\u00fc forumlar falan zaten ya\u015f\u0131 b\u00fcy\u00fck olsa da pek bir \u015fey olacak insanlar de\u011filler zaten de i\u015fte g\u00fczel olmu\u015f falan diyorlar tabii. Mod arkada\u015flar\u0131m var biraz forumda onlar da grafik ekibi diye bir \u015fey var ona alal\u0131m seni deyip duruyolar ama onun da bir olay\u0131 yok ki. Benim ilgimin o alanlara kaymas\u0131 gayet normal ben 10 ya\u015f\u0131ma kadar gayet s\u0131radan ve aptal bir insand\u0131m aptall\u0131k kal\u0131c\u0131 herhalde ama s\u0131radan olmak ile ilgili \u00e7ok \u015fey de\u011fi\u015fti ve bir c\u00fcmle ile sadece bir yerde okumu\u015ftum &#8220;D\u00fcnyadaki en kudretli insan kendini idare edebilen insand\u0131r.&#8221; Evet bu c\u00fcmle ve kimin s\u00f6yledi\u011fini bile hat\u0131rlam\u0131yorum bunu da bir yerden ald\u0131m ama \u00f6ylesine yazm\u0131\u015f bir de utanmadan derler demi\u015f kim der acaba ke\u015fke onu da yazsayd\u0131. Neyse i\u015fte tabii ben bunu okuyunca g\u00fcncelleme falan da geldi herhalde ondan sonraki d\u00f6nemlerde tabii birden de\u011fil bu s\u00fcrekli sorunlar\u0131 kendim halletmeye \u00e7al\u0131\u015ft\u0131m ve bu y\u00f6nde okudum tabii genelde bilgisayar ba\u015f\u0131ndan kalkmad\u0131\u011f\u0131m i\u00e7in oraya do\u011fru y\u00f6nelmi\u015f olabilir. \u00c7ok sa\u00e7ma ama bu s\u00f6z bana \u00e7ok \u015fey katt\u0131. Cidden \u00e7ok sa\u00e7ma ya. O y\u00fczden s\u00fcrekli bir \u015feyler hakk\u0131nda bilgi sahibi olmak istiyorum. Hem da\u011f hayat\u0131nda ya\u015famak iste\u011fim de buradan geliyor herhalde tabii zamanla da\u011f yerini \u00e7\u00f6le b\u0131raksa da. Sokaklara \u00e7\u0131kmak, h\u0131mm&#8230; Bakkala falan gidiyorum arada o say\u0131l\u0131r m\u0131? Ama \u00e7ar\u015famba g\u00fcn\u00fc de i\u015fe gitmem gerekiyordu 3 g\u00fcn gidecektim bayramdan \u00f6nce yo\u011fun oldu\u011fu i\u00e7in ama \u00e7ar\u015famba gitme iste\u011fim olmad\u0131\u011f\u0131 i\u00e7in i\u015fim var dedim tabii dedikten sonra evde durmamam gerekiyor bu sene bizim s\u0131n\u0131fta olan bir insan vard\u0131 evi de yak\u0131n bize ona s\u00f6yledim gel bir yerlere falan gidelim diye onun da i\u015fi varm\u0131\u015f zaten i\u015fte onun i\u015fini g\u00f6rmeye diye \u00e7\u0131kt\u0131m 7-8 saat salak salak y\u00fcr\u00fcd\u00fck ama iyi y\u00fcr\u00fcd\u00fck normalde y\u00fcr\u00fcmeyi \u00e7ok severim ben bile s\u0131k\u0131lm\u0131\u015ft\u0131m art\u0131k sonralara do\u011fru. \u0130yi hissetmem m\u00fcmk\u00fcn de\u011fil d\u00fcnyada onca g\u00fczel yer varken ya\u015fad\u0131\u011f\u0131m yere bak da\u011f\u0131n ba\u015f\u0131nda bir barakam olsa ve \u015fu an k\u0131\u015f haz\u0131rl\u0131\u011f\u0131 yapsam fena m\u0131 olurdu be belki yaz\u0131n et kurutmu\u015fumdur \u015fu an onu bile yiyor olabilirdim. Yaz\u0131k \u00e7ok yaz\u0131k. Tabii bu da de\u011fil beni s\u0131k\u0131nt\u0131ya s\u00fcr\u00fckleyen \u015fey her \u015fey sanki harikaym\u0131\u015f gibi geliyor tabii bu da insan\u0131n ister istemez can\u0131n\u0131 s\u0131k\u0131yor. Ama bu s\u0131k\u0131nt\u0131 bana mutluluk veriyor gibi de bir durum s\u00f6z konusu tam anlayamad\u0131m. \u00dcst\u00fcnde \u00e7al\u0131\u015f\u0131yorum. Ben de isterim \u015fiir okumak ama korkuyorum ya anlayamaz isem yaz\u0131lan\u0131 ya da yanl\u0131\u015f anlarsam diye beynimin o kadar geli\u015fmi\u015f oldu\u011fundan emin de\u011filim.<br \/>\n(Foto\u011fraf)<br \/>\nNas\u0131l yarat\u0131ld\u0131 acaba. B\u00f6yle g\u00f6zlerine mil \u00e7ekip elini t\u00fcm y\u00fcz\u00fcnde gezdirmek gerek. \u00c7ok zevkli olurdu herhalde. Biraz yanl\u0131\u015f olmu\u015f c\u00fcmle mil \u00e7ekilmesi gereken g\u00f6z elbette eli gezdirecek ki\u015finin g\u00f6z\u00fc yani zaten di\u011fer t\u00fcrl\u00fc d\u00fc\u015f\u00fcn\u00fclemezdi bile. \u00c7ok mutsuzum her c\u00fcmleden sonra ellerim klavyenin \u00fczerine d\u00fc\u015f\u00fcyor. Durduk yere yoruluyorum. D\u00fczene uymak g\u00fczel bir \u015fey mi ger\u00e7i ben de b\u00f6yle etraf\u0131 yak\u0131p y\u0131kan biriymi\u015fim gibi konu\u015fuyorum. S\u0131radan olmak \u00e7ok zor. Biliyor musun demin elim klavyeye d\u00fc\u015f\u00fcnce baz\u0131 harfler \u00e7\u0131kt\u0131 silmek zorunda kald\u0131m \u00e7ok s\u0131k\u0131c\u0131yd\u0131. Bizim burada da olaylar \u00e7\u0131kt\u0131 k\u00fcrtler falan karakola sald\u0131rmaya \u00e7al\u0131\u015fm\u0131\u015f 2 g\u00fcn \u00f6nce d\u00fcn de yine toplanm\u0131\u015f y\u00fcr\u00fcyorlarm\u0131\u015f biri bunlar\u0131n \u00fczerine mermi ya\u011fd\u0131rm\u0131\u015f sadece birinin baca\u011f\u0131na m\u0131 ne gelmi\u015f onca ki\u015fiden bir ki\u015fiyi vurmay\u0131 nas\u0131l ba\u015farm\u0131\u015f acaba. Bunu yazd\u0131m bir i\u015fim \u00e7\u0131kt\u0131 i\u015f dedi\u011fim de bo\u015f bo\u015f d\u00fc\u015f\u00fcnmek akl\u0131ma bir \u015fey geldi oturdum 2 saat onu d\u00fc\u015f\u00fcnd\u00fcm. Neyse i\u015fte 2 saat oldu ve \u015fu an biber gaz\u0131 etkisi eve kadar geldi yine toplanm\u0131\u015flar 200 ki\u015fi yoklar cinayet i\u015flemek istiyorum ama tek ba\u015f\u0131na ne anlam\u0131 var ki cinayet i\u015flesem kendimi tatmin etmek i\u00e7in i\u015flerim muhtemelen bunun i\u00e7in de yan\u0131mda birinin olup onun onaylamas\u0131 gerek. \u00c7ok s\u0131k\u0131l\u0131yorum lan. S\u0131k\u0131nt\u0131 de\u011fil asl\u0131nda bunal\u0131m m\u0131d\u0131r nedir bilemiyorum \u00e7ok ya\u015fland\u0131m belki ondand\u0131r. G\u00fcn\u00fcm\u00fczde ya\u015f\u0131yor olmam gerekti\u011finden pek emin de\u011filim. Ve s\u00fcrekli kendimi tekrarl\u0131yorum (Ama asla d\u00fc\u015f\u00fcncelerim tekrarlamaz odaklansam bile geli\u015fiyor istemsizce d\u00fc\u015f\u00fcn\u00fcyorum yanl\u0131\u015f anlama ego havas\u0131 olan bir c\u00fcmle oldu burada d\u00fc\u015f\u00fcncelerim iyi oldu\u011funu asla belirtmedim sizin de g\u00f6rd\u00fc\u011f\u00fcn\u00fcz gibi \u00e7o\u011fu gereksiz ve kullanmad\u0131\u011f\u0131m \u015feyler ama d\u00fc\u015f\u00fcn\u00fcyorum i\u015fte acaba di\u011fer insanlar da s\u00fcrekli d\u00fc\u015f\u00fcn\u00fcyor mudur. Biraz sa\u00e7ma oldu elbette d\u00fc\u015f\u00fcn\u00fcyorlard\u0131r da neyi acaba.) Bu tekrarlardan s\u0131k\u0131lm\u0131\u015f olabilirim belki. Ah ulan kimler mutlu mutluluk elde etmek istemek \u00e7ok gereksiz herhalde neden b\u00f6yle bir aray\u0131\u015f i\u00e7indeyim bilmiyorum. Muhtemelen mutsuzlu\u011fu yenmenin tek yolunun mutlu olmak i\u00e7in \u00e7abalamak oldu\u011funu d\u00fc\u015f\u00fcn\u00fcyor olabilirim. \u00c7ok garip \u00e7al\u0131\u015f\u0131yorum belki herkes \u00f6yledir ama bunu bedeni kullananlar d\u0131\u015f\u0131nda kim anlayabilir. \u0130ki sat\u0131r \u015fey yazarken bile ka\u00e7 kere bakt\u0131m foto\u011frafa bir y\u00fcz i\u00e7in bu kadar d\u00fc\u015f\u00fcnebilece\u011fim hi\u00e7 akl\u0131ma gelmezdi. Bu arada \u00e7ok \u00f6zel olacak ama senin han\u0131m nerede ikamet ediyor. Ha bir de (Asl\u0131nda burada &#8220;Ha bir de&#8221; demek yerine &#8220;Bu arada&#8221; demek isterdim ama \u00f6nceden s\u00f6ylemi\u015fim ne yaz\u0131k ki.) Hassiktir ya parantez i\u00e7ini yazarken kuraca\u011f\u0131m c\u00fcmleyi unuttum iyi mi 5 dakika d\u00fc\u015f\u00fcnmek i\u00e7in beklemek istiyorum umar\u0131m akl\u0131ma gelir. Gelmedi ya \u00f6nemli bir \u015fey olsa kesin gelirdi ben biraz daha d\u00fc\u015f\u00fcnece\u011fim bunun hakk\u0131nda.<\/p>\n<p style=\"text-align:justify;\">Okuduktan sonra elindeki telefonla bankay\u0131 ar\u0131yorsun. Teleksekreter sana hizmet kalitesinden vesaire bahsederek beklemen gerekti\u011fini s\u00f6yl\u00fcyor. On dakika bekliyorsun. \u0130mam\u0131n kitaplar\u0131na g\u00f6z gezdiriyorsun. Hep lo\u015f bir \u0131\u015f\u0131k var bu odada. Kapat\u0131p tekrar ar\u0131yorsun bankay\u0131 ve ayn\u0131 ses sana hizmet kalitesinden ve beklemen gerekti\u011finden bahsediyor tekrar. Bir on dakika daha bekliyorsun. H\u00e2l\u00e2 cevap yok. Saat sabah sekiz k\u0131rk be\u015f. Bug\u00fcn y\u00e2rinin dersi daha ge\u00e7 ba\u015flayacak. Ge\u00e7 kalkarak dinlenmeyi pl\u00e2nlad\u0131n\u0131z bu sabah i\u00e7in.<\/p>\n<p style=\"text-align:justify;\">Telefondaki ses, her yeniden aray\u0131\u015f\u0131nda hizmet kalitesinden ve beklemen gerekti\u011finden bahsediyor. Ve ard\u0131ndan m\u00fczik \u00e7al\u0131yor. Ayn\u0131 m\u00fczik bu bankan\u0131n rekl\u00e2m\u0131nda da \u00e7al\u0131yor. Yabanc\u0131 bir \u015fark\u0131n\u0131n bozuk bir T\u00fcrk\u00e7eyle yap\u0131lm\u0131\u015f uyarlamas\u0131. \u0130natla aramaya devam ediyorsun. K\u0131rk dakikada on kere ar\u0131yorsun bankay\u0131. Hizmet kalitesinden ve beklemen gerekti\u011finden bahsediyor telesekreter on kere.<\/p>\n<p style=\"text-align:justify;\">&#8220;Alo,&#8221; diyorsun.<\/p>\n<p style=\"text-align:justify;\">&#8220;Merhabalar efendim, nas\u0131l yard\u0131mc\u0131 olabilirim?&#8221; diyor bir kad\u0131n.<\/p>\n<p style=\"text-align:justify;\">&#8220;Bize hizmet verdi\u011fini s\u00f6yleyen bankaya m\u0131 yoksa Avrupa Ba\u015fkonsoloslu\u011fu&#8217;na m\u0131 ba\u011flan\u0131yorum?&#8221;<\/p>\n<p style=\"text-align:justify;\">&#8220;Buyurun efendim, ****** Bankas\u0131. Nas\u0131l yard\u0131mc\u0131 olabilirim?&#8221;<\/p>\n<p style=\"text-align:justify;\">&#8220;Bir saattir hizmet kalitenize dair bir ses kayd\u0131 dinleyerek bekletiliyorum. Yard\u0131mc\u0131 olabilece\u011finizi d\u00fc\u015f\u00fcn\u00fcyor musun?&#8221;<\/p>\n<p style=\"text-align:justify;\">&#8220;Anlamad\u0131m efendim.&#8221;<\/p>\n<p style=\"text-align:justify;\">&#8220;Bir saattir bankan\u0131za ba\u011flanmaya \u00e7al\u0131\u015f\u0131yorum. Safi m\u00fczik \u00e7alarak oyal\u0131yorsunuz.&#8221;<\/p>\n<p style=\"text-align:justify;\">&#8220;Efendim, yo\u011funluktan dolay\u0131 b\u00f6yle durumlar olabiliyor.&#8221;<\/p>\n<p style=\"text-align:justify;\">&#8220;Han\u0131mefendi, saat sabah sekizden beri ar\u0131yorum. Bu saatlerde bile bu kadar yo\u011fun oluyorsan\u0131z i\u015fleriniz \u00e7ok iyi gidiyor demektir. O halde telefonlara bakacak birini daha alabilirsiniz, de\u011fil mi?&#8221;<\/p>\n<p style=\"text-align:justify;\">Biraz sustuktan sonra konu\u015fuyor kad\u0131n:<\/p>\n<p style=\"text-align:justify;\">&#8220;Nas\u0131l yard\u0131mc\u0131 olabilirim?&#8221;<\/p>\n<p style=\"text-align:justify;\">&#8220;\u0130nat ettim ve bir saat boyunca bekledim bu telefona cevap verilmesini. Yeterince sab\u0131rl\u0131yd\u0131m. O y\u00fczden sizin de sab\u0131rl\u0131 bir \u015fekilde beni dinlemeniz gerekiyor. Fakat laf\u0131m\u0131 uzatmayaca\u011f\u0131m, daha fazla ki\u015fi &#8216;me\u015fguliyetiniz&#8217;den dolay\u0131 ma\u011fdur olsun istemiyorum. Devletten ald\u0131\u011f\u0131m e\u011fitim kredisinin g\u00fcn\u00fc ge\u00e7mesine ra\u011fmen neden h\u00e2l\u00e2 yatmad\u0131\u011f\u0131n\u0131 \u00f6\u011frenmek istiyorum.&#8221;<\/p>\n<p style=\"text-align:justify;\">&#8220;G\u00fcn i\u00e7erisinde mutlaka yatacakt\u0131r hesab\u0131n\u0131za. Bu g\u00fcnlerde birka\u00e7 s\u0131k\u0131nt\u0131 ya\u015fad\u0131k KYK kredileri konusunda. Fakat \u015fimdi halledilmi\u015ftir.&#8221;<\/p>\n<p style=\"text-align:justify;\">&#8220;Son bir \u015fey s\u00f6yleyece\u011fim. E\u011fer kredi kart\u0131 \u00e7al\u0131nan bir ki\u015fi sizi arasayd\u0131, onu da bir saat bekletecek miydiniz?&#8221;<\/p>\n<p style=\"text-align:justify;\">Son bir gayretle ve k\u00fc\u00e7\u00fck bir sinir krizi ge\u00e7irerek cevap veriyor kad\u0131n:<\/p>\n<p style=\"text-align:justify;\">&#8220;Daha \u00f6nce de belirtti\u011fim gibi, yo\u011funluktan dolay\u0131 b\u00f6yle bir \u015fey ya\u015fand\u0131.&#8221;<\/p>\n<p style=\"text-align:justify;\">&#8220;O tezinizi \u00e7\u00fcr\u00fctm\u00fc\u015ft\u00fck. Kredi kart\u0131 \u00e7al\u0131nan biri ne yapmal\u0131? \u00c7\u00fcnk\u00fc e\u011fer bir saat bekletirseniz o s\u00fcre i\u00e7erisinde b\u00fct\u00fcn limiti bitirirler, \u00f6yle de\u011fil mi?&#8221;<\/p>\n<p style=\"text-align:justify;\">&#8220;\u00d6yle bir \u015fey oldu\u011fu zaman ki\u015fi \u015fubemize gelebilir.&#8221;<\/p>\n<p style=\"text-align:justify;\">&#8220;Tabii. Hemen gelir. \u0130yi g\u00fcnler&#8221; deyip kapat\u0131yorsun telefonu. \u00d6yle mi yap\u0131yorsun?<\/p>\n<p style=\"text-align:justify;\">Derken kap\u0131y\u0131 \u00e7alarak imam giriyor odaya. Dalg\u0131nl\u0131ktan ve telefonla me\u015fguliyetten yata\u011f\u0131n\u0131 toplamay\u0131 ve oday\u0131 havaland\u0131rmay\u0131 unuttun. \u00dcstelik de \u015fimdi \u00e7\u0131k\u0131p y\u00e2rinle bulu\u015fman gerekiyor. G\u00fcnayd\u0131n diyorsunuz birbirinize. Af dilemene mahal vermeden oday\u0131 havaland\u0131r\u0131yor \u0130mam Mithat. Yine de, kusura bakmay\u0131n hocam diyerek derhal yata\u011f\u0131 topluyorsun. K\u0131saca bankayla olan telefon g\u00f6r\u00fc\u015fmeni anlatarak gitmen gerekti\u011fini s\u00f6yl\u00fcyorsun. Ve \u00e7\u0131k\u0131p park\u0131n orada bulu\u015fuyorsunuz y\u00e2rinle.<\/p>\n<p style=\"text-align:justify;\">&#8220;G\u00fcnayd\u0131n genc-i nih\u00e2n\u0131m&#8221; diyorsun. G\u00fcl\u00fcms\u00fcyorsunuz. Otob\u00fcse giden yolda ilerlerken &#8220;Hayat\u0131m b\u00f6yle kals\u0131n,&#8221; diyorsun. &#8220;Seninle sabah okula gideyim. Sen dersteyken seni bekleyeyim. Beklerken de seni beklemenin sevinciyle \u015fiirler okuyay\u0131m. Okulun ard\u0131ndan birlikte bir \u015feyler yapal\u0131m. Birlikte dil \u00f6\u011frenelim, ders \u00e7al\u0131\u015fal\u0131m, keman \u00e7alal\u0131m, bir \u015feyler anlatal\u0131m, anlatal\u0131m ve anlatal\u0131m. Hayat\u0131m b\u00f6yle ge\u00e7sin. Ben b\u00f6yle \u00e7ok mutluyum. Okula filan d\u00f6nmek istemiyorum. Okul aptal bir yer. T\u00fcm kurumlar do\u011fduklar\u0131 sebeplerden sapm\u0131\u015f durumda, \u00e7\u0131kar amac\u0131yla do\u011fanlar hari\u00e7.&#8221; Dinliyor y\u00e2rin seni. Bu laflar\u0131n\u0131n onda iltifat hissi uyand\u0131rd\u0131\u011f\u0131n\u0131 d\u00fc\u015f\u00fcn\u00fcyorsun. Fakat senin amac\u0131n bu de\u011fil. Sen dertli bir insans\u0131n. Edece\u011fin her iltifat bu derdine ihanet olur.<\/p>\n<p style=\"text-align:justify;\"><span style=\"color:var(--color-text);\">Telefonun \u00e7al\u0131yor. Annendir.<\/span><\/p>\n<p style=\"text-align:justify;\">Annen.<\/p>\n<p style=\"text-align:justify;\">&#8220;Alo, o\u011flum!&#8221;<\/p>\n<p style=\"text-align:justify;\">&#8220;Buyur anne&#8230;&#8221;<\/p>\n<p style=\"text-align:justify;\">K\u0131sa bir h\u00e2l ve hat\u0131r seromonisinden sonra yolculuk nas\u0131ld\u0131 seromonisine ge\u00e7iyorsunuz. Ve arada annen sana sebeb-i aray\u0131\u015f\u0131yla ilgili bir \u015fey s\u00f6yl\u00fcyor: &#8220;O\u011flum, askerlik k\u00e2\u011f\u0131d\u0131n gelmi\u015f!&#8221;<\/p>\n<p style=\"text-align:justify;\">&#8220;Ne yaz\u0131yor?&#8221; diye sakinlikle soruyorsun.<\/p>\n<p style=\"text-align:justify;\">&#8220;Yoklamaya t\u00e2bi yaz\u0131yor. En yak\u0131n askerlik \u015fubesine gidecekmi\u015fsin. En ge\u00e7 2 May\u0131s tarihi yaz\u0131yor&#8221; diye anlat\u0131yor annen ve ard\u0131ndan k\u00e2\u011f\u0131d\u0131 ba\u015ftan sona okuyor.<\/p>\n<p style=\"text-align:justify;\">&#8220;Bir kar\u0131\u015f\u0131kl\u0131k olmu\u015f olmal\u0131,&#8221; diyorsun. &#8220;\u00dcniversite, okudu\u011fuma dair belgeyi g\u00f6ndermedi herh\u00e2lde.&#8221;<\/p>\n<p style=\"text-align:justify;\">&#8220;Herh\u00e2lde&#8221; diye dal\u0131p gidiyor annen. Sesinden, \u00fcz\u00fcld\u00fc\u011f\u00fc ve endi\u015felendi\u011fi anla\u015f\u0131l\u0131yor. O\u011flunun gelen askerlik k\u00e2\u011f\u0131d\u0131 ona bir s\u00fcr\u00fc \u015fey d\u00fc\u015f\u00fcnd\u00fcrm\u00fc\u015f olmal\u0131. Do\u011fuya gidece\u011fin, operasyonlara kat\u0131laca\u011f\u0131n ve bir \u00e7at\u0131\u015fmada \u00f6lece\u011fin. Bunlar\u0131 d\u00fc\u015f\u00fcnmenin ona bu hisleri vermi\u015f olmas\u0131 gayet tabii.<\/p>\n<p style=\"text-align:justify;\">&#8220;Ben icab\u0131na bakar\u0131m anne, merak etme&#8221; diyorsun. Annen biraz daha rahatlayarak normalle\u015fmeye ba\u015fl\u0131yor. Sorular\u0131 eski h\u00e2le d\u00f6n\u00fcyor. &#8220;Ne yap\u0131yorsunuz? E\u011fleniyor musunuz? K\u0131z\u0131m nas\u0131l, iyi mi?&#8221; gibi \u015feyler.<\/p>\n<p style=\"text-align:justify;\">Annen \u00e7ok h\u0131zl\u0131ca duygu de\u011fi\u015fimleri ya\u015fayan bir insan. K\u0131r\u0131lgan ve fakat k\u0131r\u0131c\u0131 birisi. Vicdan\u0131 sapasa\u011flamd\u0131r fakat onu dinlememek i\u00e7in \u00e7abalayabilecek birisidir ayn\u0131 zamanda. \u0130lk be\u015f dakika a\u011flayacak gibiyken di\u011fer be\u015f dakikada so\u011fukkanl\u0131 bir h\u00e2l alarak g\u00fcnl\u00fck \u015feylerden bahsetmeye ba\u015flar. Anla\u015f\u0131lamaz h\u00e2l ve tav\u0131rlar\u0131. \u00dcstelik kar\u015f\u0131s\u0131ndakinin de kendisi gibi olmas\u0131n\u0131 bekler.<\/p>\n<p style=\"text-align:justify;\">Telefonu kapatt\u0131ktan sonra y\u00e2rine de durumu anlat\u0131yorsun. Askerlikle ilgili konularda epeyi endi\u015felenen birisi y\u00e2rin. Yanl\u0131\u015f ve ac\u0131mas\u0131z bir durum oldu\u011funu s\u00f6yl\u00fcyor. Haks\u0131z oldu\u011funu s\u00f6yleyemezsin asla. Zira sava\u015f\u0131n bile bir takti\u011fi vard\u0131r.<\/p>\n<p style=\"text-align:justify;\">Hemen gidelim diyor y\u00e2rin. En yak\u0131ndaki askerlik \u015fubesini kastediyor. Okula gitmelisiniz, y\u00e2rinin dersi var. Gitmeyece\u011finizi s\u00f6yl\u00fcyor y\u00e2rin. Israr etmek istiyorsun ama o da b\u00f6yle bir durumda dersten bir \u015fey anlayamayaca\u011f\u0131n\u0131 s\u00f6yl\u00fcyor. O zaman bu i\u015fi \u00e7\u00f6zd\u00fckten sonra daha rahat bir kafayla birlikte \u00e7al\u0131\u015f\u0131r\u0131z hocan\u0131n i\u015fledi\u011fi yerlere, diyorsun. Olur, diyor.<\/p>\n<p style=\"text-align:justify;\">En yak\u0131ndaki askerlik \u015fubesine gidiyorsunuz. Fakat yanl\u0131\u015fl\u0131kla asker\u00ee lojmanlar\u0131n kap\u0131s\u0131ndan girmeye \u00e7al\u0131\u015f\u0131yorsunuz. Kap\u0131ya yakla\u015fmadan baya\u011f\u0131 \u00f6teden askerlerden biri t\u00fcfe\u011fine sar\u0131larak &#8220;Orada kal\u0131n!&#8221; diye sesleniyor. &#8220;Askerlik k\u00e2\u011f\u0131d\u0131m gelmi\u015f, onun i\u00e7in geldik&#8221; diye ayn\u0131 ses tonuyla kar\u015f\u0131l\u0131k veriyorsun. &#8220;A\u015fa\u011f\u0131ki kap\u0131dan gireceksiniz&#8221; diyerek tarif ediyor er ki\u015fi.<\/p>\n<p style=\"text-align:justify;\">A\u015fa\u011f\u0131dan giriyorsunuz ve y\u00e2rine, bah\u00e7enin i\u00e7erisindeki bir bankta beklemesini s\u00f6yl\u00fcyorsun. \u0130lk olarak g\u00fcvenlikle muhatap olmak zorundas\u0131n. G\u00fcvenli\u011fe durumu izah ediyorsun ve o da senin bu i\u015fini iki saniyede halledebilecekmi\u015f gibi bak\u0131yor sana. Ard\u0131ndan kimli\u011fine bak\u0131yor. Burada dura dura \u00f6\u011frenmi\u015f memur fiyakal\u0131\u011f\u0131n\u0131. A\u011f\u0131r a\u011f\u0131r ve kendinden emin ve sana ger\u00e7ekten yard\u0131mc\u0131 olabilecekmi\u015f gibi davran\u0131yor. Bu hareketleri uzad\u0131k\u00e7a seninle dalga ge\u00e7ti\u011fini d\u00fc\u015f\u00fcn\u00fcyorsun. Camdan i\u00e7eriye bak\u0131yorsun: \u0130\u00e7eride bir\u00e7ok ki\u015fi var.<\/p>\n<p style=\"text-align:justify;\">&#8220;\u0130\u00e7eriden yard\u0131mc\u0131 olsunlar sana&#8221; diyor g\u00fcvenlik g\u00f6revlisi. &#8220;S\u0131ra beklemem gerekiyor mu?&#8221; diye soruyorsun. Do\u011frudan girip sorabilece\u011fini s\u00f6yl\u00fcyor. Kimli\u011fini al\u0131p i\u00e7eriye giriyorsun. Banka gibi bir yere geldi\u011fini g\u00f6r\u00fcyorsun. Akl\u0131n\u0131n bir k\u0131sm\u0131 da y\u00e2rinde. O y\u00fczden h\u0131zl\u0131 olmaya gayret g\u00f6steriyorsun.<\/p>\n<p style=\"text-align:justify;\">Bir kad\u0131na gidip merhaba diyorsun. Bu numaralar\u0131 yemem der gibi bak\u0131yor sana ve ne s\u00f6yleyeceksen s\u00f6yle manas\u0131nda &#8220;Buyrun&#8221; diyor. Durumu izah ediyorsun. Okudu\u011funu, hatta e\u011fitim kredisi ald\u0131\u011f\u0131n\u0131, buna ra\u011fmen nas\u0131l olur da askere \u00e7a\u011fr\u0131ld\u0131\u011f\u0131n\u0131 anlat\u0131yorsun k\u0131saca. Kayd\u0131na bak\u0131yor ve &#8220;Pazartesi yoklama yap\u0131l\u0131r. E\u011fer yoksan asker ka\u00e7a\u011f\u0131 g\u00f6z\u00fck\u00fcrs\u00fcn&#8221; diyor.<\/p>\n<p style=\"text-align:justify;\">\u00a0&#8220;Fakat ben \u00f6\u011frenciyim, askerlikle ne i\u015fim var?&#8221; diyorsun.<\/p>\n<p style=\"text-align:justify;\">&#8220;Burada \u00f6yle g\u00f6z\u00fckm\u00fcyor. Yoklamaya t\u00e2bi diyor. Okulun senin okudu\u011funa dair bir k\u00e2\u011f\u0131t g\u00f6ndermemi\u015f.&#8221;<\/p>\n<p style=\"text-align:justify;\">&#8220;\u00d6\u011frenci belgesi getirsem \u00e7\u00f6z\u00fcl\u00fcr m\u00fc peki bu hata?&#8221;<\/p>\n<p style=\"text-align:justify;\">&#8220;Burada bir hata g\u00f6z\u00fckm\u00fcyor. Ama e\u011fer okuyorsan, tabii, \u00f6\u011frenci belgesi getirdi\u011finde hallolur bu durum. En ge\u00e7 yar\u0131n getirmelisin. Pazartesiye kal\u0131rsa yok yaz\u0131l\u0131rs\u0131n ve ondan sonra da para cezas\u0131 i\u015flemeye ba\u015flar.&#8221;<\/p>\n<p style=\"text-align:justify;\">&#8220;Eyvah! Buraya geleli iki dakika oldu ama \u015fimdiden asker ka\u00e7a\u011f\u0131 il\u00e2n edildim ve para cezas\u0131na \u00e7arpt\u0131r\u0131ld\u0131m. \u00d6\u011frenci belgesini yar\u0131na kadar getirmem m\u00fcmk\u00fcn de\u011fil. U\u00e7akla okula gidip gelmem gerekiyor. Ve oraya gitmeme daha d\u00f6rt g\u00fcn var. Havaalan\u0131nda problem olur mu polislerle?&#8221;<\/p>\n<p style=\"text-align:justify;\">&#8220;Olur. Polis kontrol\u00fcnden ge\u00e7emezsin. Asker ka\u00e7a\u011f\u0131 g\u00f6r\u00fcnd\u00fc\u011f\u00fcn i\u00e7in yakalan\u0131rs\u0131n.&#8221;<\/p>\n<p style=\"text-align:justify;\">&#8220;Vay ba\u015f\u0131ma gelenler! \u015eimdi de tutukland\u0131m. Neyse, iyisi mi, ben gidip e\u015fimle vedala\u015fay\u0131m. Belli ki devlet ak\u0131l yerine b\u00fcrokrasiyi, vicdan yerine de memurlar\u0131 koymu\u015f mekanizmas\u0131na.&#8221;<\/p>\n<p style=\"text-align:justify;\">Bah\u00e7eye \u00e7\u0131k\u0131p y\u00e2rinin yan\u0131na gidiyorsun. Merakla ne oldu\u011funu soruyor. Bu konularda ne kadar endi\u015felendi\u011fini bildi\u011finden i\u00e7ine su serpecek \u015feyler s\u00f6ylemek istiyorsun ama senin bile i\u00e7ine ate\u015f d\u00fc\u015fm\u00fc\u015f durumda. Sakince izah ediyorsun. \u00c7\u0131ld\u0131racak gibi oluyor. Kolundan tutuyor ve tekrar gidip, ba\u015fkas\u0131na sorman\u0131 istiyor. Dedi\u011fini yapacaks\u0131n. En nihayetinde y\u00e2rinle bir da\u011fa \u00e7\u0131k\u0131p devletin sizi bulamayaca\u011f\u0131 bir hayat ya\u015famak var.<\/p>\n<p style=\"text-align:justify;\">Bu kez en k\u00f6\u015fede oturan adama gidiyorsun. Birinin i\u015fini bitirmek \u00fczere. Seni bekletiyor. Sakat a\u011fbisini askere \u00e7a\u011f\u0131rd\u0131klar\u0131n\u0131 anlat\u0131yor bir \u00e7ocuk.<\/p>\n<p style=\"text-align:justify;\">Birazdan sana d\u00f6n\u00fcyor adam ve a\u011fz\u0131ndan isteksiz ve \u015fevk k\u0131r\u0131c\u0131 bir kelime bile \u00e7\u0131kmas\u0131na izin vermeden durumunu izah ediyorsun. Ayn\u0131 \u015fekilde sisteme girerek ger\u00e7ekten askere \u00e7a\u011f\u0131r\u0131ld\u0131\u011f\u0131n\u0131 teyit ediyor. Okuyor musun diyor. Evet. Ka\u00e7\u0131nc\u0131 s\u0131n\u0131ftas\u0131n diyor. \u0130ki. Daha yenisin \u00fcstelik diyor. Do\u011fru.<\/p>\n<p style=\"text-align:justify;\">&#8220;Bir \u015fey olmaz&#8221; diyor adam. Ve devam ediyor: &#8220;Pazartesi g\u00fcnk\u00fc yoklamada yok yaz\u0131l\u0131rs\u0131n ve y\u00fcz lira kadar bir para cezas\u0131 yaz\u0131l\u0131r. Fakat o da okuldan k\u00e2\u011f\u0131t gelince silinir. Zaten senlik bir mesele de\u011fil bu. Okulla aram\u0131zda hallediyoruz biz. Fakat bu aralar birka\u00e7 okulla b\u00f6yle s\u0131k\u0131nt\u0131lar ya\u015fad\u0131k. Ge\u00e7 yollad\u0131lar bilgileri. Seninki de \u00f6yle olur. Merak etme.&#8221;<\/p>\n<p style=\"text-align:justify;\">&#8220;D\u00f6rt g\u00fcn sonra u\u00e7a\u011f\u0131m var. Polis kontrol\u00fcnde bir problem \u00e7\u0131kar m\u0131 peki?&#8221;<\/p>\n<p style=\"text-align:justify;\">&#8220;Hi\u00e7bir \u015fey olmaz. \u00d6\u011frenci kimli\u011fini g\u00f6sterirsin, o yeter.&#8221;<\/p>\n<p style=\"text-align:justify;\">Te\u015fekk\u00fcr ederek ayr\u0131l\u0131yorsun oradan ve y\u00e2rinin yan\u0131na gidiyorsun. Ne oldu\u011funu soruyor y\u00e2rin heyecanla. &#8220;Devletin kafas\u0131 kar\u0131\u015f\u0131k&#8221; diyorsun dalg\u0131n bir \u015fekilde. Sonra olanlar\u0131 anlat\u0131yorsun. &#8220;Ger\u00e7ekten,&#8221; diyor y\u00e2rin. &#8220;Devletin kafas\u0131 kar\u0131\u015f\u0131k.&#8221; Kendi i\u00e7erisindeki kurumlarda dahi sa\u00e7ma bir \u00e7eli\u015fki i\u00e7erisindeler. Yaln\u0131zca k\u00f6t\u00fcl\u00fckte ittifak edebiliyorlar. Ya da insanlar\u0131 ilgilendirmeyen konularda. Bor\u00e7lu insanlara, &#8220;Ba\u015fkanl\u0131k sistemine ge\u00e7ilsin mi?&#8221; diye sorulabiliyor mesel\u00e2. Bu konular \u00fczerine konu\u015fuyorsunuz.<\/p>\n<p style=\"text-align:justify;\">Daha sonra oradan ayr\u0131larak yurdun \u00e7evresindeki parka gidiyorsunuz y\u00e2rinin bug\u00fcnk\u00fc dersine \u00e7al\u0131\u015fmak i\u00e7in.<\/p>"},"thr:total":"1","comments":{"commentCount":"bir","comments":[{"imgUrl":"https:\/\/0.gravatar.com\/avatar\/0aa5ff0c1a37186f62b49b8c730b1cb3?s=60&#038;d=identicon&#038;r=G","commenterName":"<a href='http:\/\/felsefeuzmani.wordpress.com' rel='external nofollow ugc' class='url'>Realist Bir Nihilist<\/a>","dateTime":"2021-03-18T15:23:57+03:00","commentBody":"Bu kitab\u0131 kim yazd\u0131? KvL deki iki abiden birimi &#8220;Olacak olana a\u011f\u0131t&#8221; bu ve di\u011fer \u015fiirleri yazan abimiz. Bir \u015fark\u0131da &#8220;bankalar vurdu babam\u0131&#8221; demi\u015fti yoksa Hira o mu ya da kendi hikayesinimi bir kitap olarak sunmu\u015f<br \/>\nKitaba d\u00fcn ba\u015flad\u0131m ve acaba diyerekten bu sorular\u0131 sordum, tabi daha kitaptan konu\u015fmad\u0131m ger\u00e7ekten benim akl\u0131mdan, hayat\u0131mdan izler ta\u015f\u0131yor","commentLikeCount":"1"}]}}