{"author":{"name":"kvl","uri":"https:\/\/kvlrap.wordpress.com"},"title":{"@type":"html","$":"Birthday Boy, Jerome David Salinger"},"link":[{"@rel":"alternate","@type":"text\/html","@href":"https:\/\/kvlrap.wordpress.com\/2020\/10\/05\/birthday-boy-jerome-david-salinger\/"},{"@rel":"replies","@type":"text\/html","@href":"https:\/\/kvlrap.wordpress.com\/2020\/10\/05\/birthday-boy-jerome-david-salinger\/#comments","@thr:count":"0"},{"@rel":"replies","@type":"application\/atom+xml","@href":"https:\/\/kvlrap.wordpress.com\/2020\/10\/05\/birthday-boy-jerome-david-salinger\/feed\/atom\/","@thr:count":"0"}],"id":"http:\/\/kvlrap.wordpress.com\/?p=2385","updated":"2020-04-23T17:49:51Z","published":"2020-10-05T17:49:09Z","category":[{"@scheme":"https:\/\/kvlrap.wordpress.com","@term":"Terceme"},{"@scheme":"https:\/\/kvlrap.wordpress.com","@term":"Yaz\u0131lar"},{"@scheme":"https:\/\/kvlrap.wordpress.com","@term":"Hik\u00e2yeler"}],"summary":{"@type":"html","$":"DO\u011eUM G\u00dcN\u00dc \u00c7OCU\u011eU Collins han\u0131m odadan \u00e7\u0131karken, her iki elinde de yemek tepsisi oldu\u011fu i\u00e7in, arkas\u0131ndaki \u00e7ift tarafl\u0131 kap\u0131y\u0131 kapatmakta biraz zorluk \u00e7ekiyor gibiydi. Odaya do\u011fru ilerleyen Ethel, ne zaman gelse, Collins han\u0131m\u2019\u0131 hep o odadan \u00e7\u0131karken g\u00f6r\u00fcyordu. \u201cBug\u00fcn nas\u0131l?\u201d diye hastane f\u0131s\u0131lt\u0131s\u0131yla sordu Ethel. \u201cAh, Bayan Nicolson!\u201d diye sanki aradan koca bir yirmi y\u0131l &#8230; <a href=\"https:\/\/kvlrap.wordpress.com\/2020\/10\/05\/birthday-boy-jerome-david-salinger\/\" class=\"more-link\">Okumaya devam et <span class=\"screen-reader-text\">Birthday Boy, Jerome David&#160;Salinger<\/span><\/a>"},"content":{"@type":"html","$":"<p style=\"text-align:center;\">DO\u011eUM G\u00dcN\u00dc \u00c7OCU\u011eU<\/p>\n<p style=\"text-align:justify;\">Collins han\u0131m odadan \u00e7\u0131karken, her iki elinde de yemek tepsisi oldu\u011fu i\u00e7in, arkas\u0131ndaki \u00e7ift tarafl\u0131 kap\u0131y\u0131 kapatmakta biraz zorluk \u00e7ekiyor gibiydi. Odaya do\u011fru ilerleyen Ethel, ne zaman gelse, Collins han\u0131m\u2019\u0131 hep o odadan \u00e7\u0131karken g\u00f6r\u00fcyordu.<\/p>\n<p style=\"text-align:justify;\">\u201cBug\u00fcn nas\u0131l?\u201d diye hastane f\u0131s\u0131lt\u0131s\u0131yla sordu Ethel.<\/p>\n<p style=\"text-align:justify;\">\u201cAh, Bayan Nicolson!\u201d diye sanki aradan koca bir yirmi y\u0131l ge\u00e7mi\u015f gibi y\u00fcksek sesle selamlayarak kar\u015f\u0131lad\u0131 Collins han\u0131m, Bayan Nicholson\u2019\u0131. \u201c\u00c7ok \u015f\u00fck\u00fcr, biraz daha iyi.\u201d Hep biraz daha iyiydi. En geni\u015f taba\u011f\u0131 ivedilikle kavrad\u0131 Collins han\u0131m. \u201cDaha \u015fimdi \u00f6\u011flen yeme\u011fini yedi, bir pirzola ve patates. Ama havu\u00e7lara hi\u00e7 dokunmad\u0131.\u201d Hep bir \u015feylere dokunmam\u0131\u015f olurdu.<\/p>\n<p style=\"text-align:justify;\">\u201cBir dakikal\u0131\u011f\u0131na i\u00e7eri girebilir miyim acaba?\u201d diye sordu Ethel. \u201cYani uyumuyor de\u011fil mi?\u201d \u201cUyumak m\u0131?\u201d dedi Collins Han\u0131m. \u201cBu adam m\u0131?\u201d<\/p>\n<p style=\"text-align:justify;\">Ethel sessizce odaya girdi. Ray, ba\u015f\u0131na payanda ile desteklenerek oturma pozisyonu verilmi\u015f yata\u011f\u0131nda oturuyordu. A\u00e7\u0131k kahverengi sa\u00e7lar\u0131, annesi yapm\u0131\u015f gibi titizlikle taranm\u0131\u015f, puantiyeli k\u0131yafetinin yakalar\u0131, sakals\u0131z g\u0131d\u0131s\u0131na do\u011fru \u00e7ekilmi\u015fti.<\/p>\n<p style=\"text-align:justify;\">Ethel\u2019e do\u011fru bakt\u0131 Ray, y\u00fcz\u00fcndeki donuk ifade hi\u00e7 de\u011fi\u015fmemi\u015fti. Sanki orada \u00f6ylece oturmak onun mesle\u011fiymi\u015f gibi duruyordu.<\/p>\n<p style=\"text-align:justify;\">\u201cEthel geldi. Selam, can\u0131m\u0131n i\u00e7i.\u201d Bu arada iki tarafl\u0131 i\u00e7 kap\u0131y\u0131 kapat\u0131yordu. \u201cBenim oturakl\u0131 tatl\u0131m.\u201d Ray\u2019in \u00fczerine do\u011fru ilerledi Ethel, e\u011fildi ve a\u011fz\u0131n\u0131 kare \u015fekline getirerek, MMmm sesiyle birlikte \u0131slac\u0131k \u00f6pt\u00fc, sanki Bay Pierce, d\u00fckk\u00e2nda, 50\u2019li y\u0131llarda ona bir apartman dairesi hediye etmi\u015f gibi sevin\u00e7le b\u00fcy\u00fck bir hareket yapt\u0131. \u201c\u0130yi ki do\u011fdun, sevgilim. \u0130yi ki, iyi ki, iyi ki, iyi ki do\u011fdun.\u201d<\/p>\n<p style=\"text-align:justify;\">\u201cSa\u011f ol. Hey. Karn\u0131ma bast\u0131r\u0131yorsun.\u201d<\/p>\n<p style=\"text-align:justify;\">Ethel, yata\u011f\u0131n yan\u0131ndaki sandalyeye oturarak Ray\u2019in elini kendi ellerinin aras\u0131na ald\u0131.<\/p>\n<p style=\"text-align:justify;\">\u201cDo\u011fum g\u00fcn\u00fc \u00e7ocu\u011fum benim.\u201d<\/p>\n<p style=\"text-align:justify;\">\u201cAh.\u201d<\/p>\n<p style=\"text-align:justify;\">\u201cNeden havu\u00e7lar\u0131n\u0131 yemedin? S\u00f6yler misin l\u00fctfen?\u201d<\/p>\n<p style=\"text-align:justify;\">\u201cBana getirmeden \u00f6nce birisi \u00e7i\u011fnemi\u015f.\u201d Ethel ustal\u0131kla, k\u0131k\u0131r k\u0131k\u0131r g\u00fcld\u00fc.<\/p>\n<p style=\"text-align:justify;\">\u201cCollins han\u0131m\u2019d\u0131r muhtemelen. Etrafta, insanlar\u0131n havu\u00e7lar\u0131n\u0131 yiyecekmi\u015f gibi dolan\u0131yor. \u00d6zellikle yirmi iki ya\u015f\u0131na basan do\u011fum g\u00fcn\u00fc \u00e7ocuklar\u0131n\u0131n havu\u00e7lar\u0131n\u0131.<\/p>\n<p style=\"text-align:justify;\">Ray homurdand\u0131.<\/p>\n<p style=\"text-align:justify;\">\u201cTatl\u0131m, yemelisin,\u201d dedi Ethel.<\/p>\n<p style=\"text-align:justify;\">Ray elini \u00e7ekip solundaki pencereden d\u0131\u015far\u0131ya bakt\u0131. Binan\u0131n di\u011fer taraf\u0131 g\u00f6z\u00fck\u00fcyordu.<\/p>\n<p style=\"text-align:justify;\">\u201cBana bak,\u201d diye ikaz etti Ethel. \u201cYirmi iki. Bana yeti\u015fiyorsun neredeyse.\u201d Kafas\u0131n\u0131n arkas\u0131ndaki kalkm\u0131\u015f sa\u00e7\u0131n\u0131 d\u00fczeltti Ray. \u201cHey, bana bak,\u201d dedi Ethel.<\/p>\n<p style=\"text-align:justify;\">\u201cAllah\u0131m Yarabbim ya.\u201d<\/p>\n<p style=\"text-align:justify;\">\u201cHay\u0131r, Ray. Bana bak.\u201d<\/p>\n<p style=\"text-align:justify;\">A\u011fz\u0131n\u0131 ard\u0131na kadar a\u00e7m\u0131\u015f, yapmac\u0131k bir g\u00fcl\u00fc\u015fle, birden Ethel\u2019a do\u011fru d\u00f6nd\u00fc Ray. Ethel g\u00fcld\u00fc. Sonra da g\u00f6zlerini sersemce yata\u011f\u0131n\u0131n ucuna do\u011fru dikti Ray.<\/p>\n<p style=\"text-align:justify;\">\u201cCollins han\u0131m\u0131n bana \u2018Bayan Nicolson\u2019 deyi\u015fini duyman gerekiyor. Her s\u00f6yleyi\u015finde \u00f6ld\u00fcr\u00fcyorum beni.\u201d<\/p>\n<p style=\"text-align:justify;\">\u201cNefret ediyorum ondan,\u201d diye bildirdi Ray, her zamanki monotonlu\u011fuyla. \u201cOnun o c\u00fcretk\u00e2rl\u0131\u011f\u0131ndan nefret ediyorum.\u201d<\/p>\n<p style=\"text-align:justify;\">\u201c\u00c7illeri var. T\u0131pk\u0131 benim gibi.\u201d<\/p>\n<p style=\"text-align:justify;\">Ray bunun \u00fczerine d\u00fc\u015f\u00fcnmeye koyulmu\u015f gibiydi. Sonra sol taraf\u0131n\u0131 ka\u015f\u0131mak i\u00e7in elini a\u015fa\u011f\u0131ya do\u011fru g\u00f6t\u00fcrd\u00fc.<\/p>\n<p style=\"text-align:justify;\">\u201cBaban geldi mi bug\u00fcn?\u201d diye sordu Ethel.<\/p>\n<p style=\"text-align:justify;\">\u201cEvet. Beni ne\u015felendirmek i\u00e7in u\u011frad\u0131. Bu ay ne kadar para kaybetti\u011fini anlatt\u0131.\u201d<\/p>\n<p style=\"text-align:justify;\">\u201cSana bir kitap getirdim,\u201d dedi Ethel. \u201cBu arada hediyen bu de\u011fil. O hen\u00fcz gelmedi. Ama beklersen g\u00f6receksin. Harika bir \u015fey. Ke\u015fke benim de bir tane olsayd\u0131.\u201d<\/p>\n<p style=\"text-align:justify;\">\u201cAynen. L\u00fctfen art\u0131k kol saati verme bana. \u00dc\u00e7 tane kol saatim var.\u201d<\/p>\n<p style=\"text-align:justify;\">\u201cKol saati de\u011fil. Baban ne hediye etti?\u201d<\/p>\n<p style=\"text-align:justify;\">\u201cHi\u00e7bir \u015fey. Do\u011fum g\u00fcn\u00fcm oldu\u011funu bilmiyordu. Getirdi\u011fin kitap ne?\u201d<\/p>\n<p style=\"text-align:justify;\">\u201cS\u00f6ylemedin mi do\u011fum g\u00fcn\u00fcn oldu\u011funu. Kesin sekreteri biliyordur!\u201d<\/p>\n<p style=\"text-align:justify;\">\u201cNe kitab\u0131 o?\u201d dedi Ray.<\/p>\n<p style=\"text-align:justify;\">Kuca\u011f\u0131ndaki kitaba bakt\u0131 Ethel.<\/p>\n<p style=\"text-align:justify;\">\u201c<em>Seninim Cennet<\/em>. Phyllis \u00f6d\u00fcn\u00e7 verdi. Hayranm\u0131\u015f bu kitaba. Sana okumam\u0131 ister misin?\u201d<\/p>\n<p style=\"text-align:justify;\">\u201cM\u00fcstehcen mi?\u201d<\/p>\n<p style=\"text-align:justify;\">\u201cSormad\u0131m,\u201d dedi Ethel, diyaloglara bakt\u0131 sayfalar\u0131 kar\u0131\u015ft\u0131rarak.<\/p>\n<p style=\"text-align:justify;\">\u201cM\u00fcstehcen b\u00f6l\u00fcmlerden birini oku.\u201d<\/p>\n<p style=\"text-align:justify;\">\u201cBa\u015f\u0131ndan ba\u015flayaca\u011f\u0131m.\u201d<\/p>\n<p style=\"text-align:justify;\">Ethel sesli bir \u015fekilde okumaya ba\u015flam\u0131\u015ft\u0131, okuyu\u015fu ne iyiydi ne de k\u00f6t\u00fc. \u0130lk b\u00f6l\u00fcm \u015f\u00f6yleydi:<\/p>\n<p style=\"text-align:justify;\">Stephen Dwight, g\u00fcderi eldivenlerini ellerine ge\u00e7irmi\u015f ve bir taksiye, durmas\u0131 i\u00e7in i\u015faret etmi\u015fti. \u201cNereye, beyefendi?\u201d diye sordu kirli taksi \u015fof\u00f6r\u00fc. \u201cKule Apartmanlar\u0131, olabildi\u011fince h\u0131zl\u0131 git,\u201d diye talimat verdi amirane, yank\u0131l\u0131 sesiyle Stephen Dwight.<\/p>\n<p style=\"text-align:justify;\">\n<p style=\"text-align:justify;\">\u201cDinle,\u201d diye okumay\u0131 b\u00f6ld\u00fc Ray. \u201cSteven Dwight\u2019la ve onun eldivenleriyle ne yapabilece\u011fini biliyorsun.\u201d<\/p>\n<p style=\"text-align:justify;\">Ethel sahte bir ah etti ve kitab\u0131 kapatt\u0131. \u201c\u00c7at\u0131ya \u00e7\u0131kt\u0131n m\u0131 bu sabah?\u201d diye sordu.<\/p>\n<p style=\"text-align:justify;\">\u201cHay\u0131r. Evet.\u201d<\/p>\n<p style=\"text-align:justify;\">\u201c\u00c7\u0131kt\u0131n m\u0131 \u00e7\u0131kmad\u0131n m\u0131?<\/p>\n<p style=\"text-align:justify;\">\u201c\u00c7\u0131kt\u0131m. Takmadan dinledi\u011fim ya\u015fl\u0131 bir adam\u0131n yan\u0131nda dola\u015ft\u0131rd\u0131lar beni.\u201d<\/p>\n<p style=\"text-align:justify;\">\u201cNe konu\u015ftu ki adam? Ne sorunu vard\u0131?\u201d<\/p>\n<p style=\"text-align:justify;\">\u201cBilmiyorum. Gallstonlar. Yale\u2019de okuyan, bana benzeyen bir \u00e7ocu\u011fu var. Tek fark, o sa\u011fl\u0131kl\u0131, kap\u0131 gibi. Ka\u00e7 ya\u015f\u0131nday\u0131m, ne yap\u0131yorum ve ne hastal\u0131\u011f\u0131m var falan filan. Hey Allah\u0131m.\u201d<\/p>\n<p style=\"text-align:justify;\">\u201cSen ne dedin?\u201d diye \u00f6\u011frenmek istedi Ethel.<\/p>\n<p style=\"text-align:justify;\">\u201cBenim ne dedi\u011fimin ne \u00f6nemi var?\u201d<\/p>\n<p style=\"text-align:justify;\">\u201cKimse fark edemez mi seni? Ya\u015fl\u0131 Joe Rotogravure.\u201d<\/p>\n<p style=\"text-align:justify;\">\u201cHay\u0131r. Bir sigara versene,\u201d dedi Ray.<\/p>\n<p style=\"text-align:justify;\">Ethel el \u00e7antas\u0131ndan \u00e7\u0131kard\u0131\u011f\u0131 deri bir kutunun i\u00e7inden bir sigara ald\u0131, sigaray\u0131 yakt\u0131, rujuna dikkat ederek. Kalkt\u0131, yata\u011f\u0131n ucuna oturdu ve sigaray\u0131, Ray\u2019in dudaklar\u0131n\u0131n aras\u0131na yerle\u015ftirdi. G\u00f6zleri kapal\u0131 bir \u015fekilde iki defa derin derin i\u00e7ine \u00e7ekti Ray, sonra normal bir \u015fekilde i\u00e7meye devam etti, pencereden d\u0131\u015far\u0131ya bakarak. Sonunda Ethel\u2019a do\u011fru d\u00f6nd\u00fc yava\u015f\u00e7a. A\u011fz\u0131n\u0131n \u015fekli cans\u0131zl\u0131\u011f\u0131ndan hi\u00e7bir \u015fey kaybetmemi\u015fti, fakat g\u00f6zleri bu\u011fuland\u0131.<\/p>\n<p style=\"text-align:justify;\">\u201cBeni bu aptal yataktan \u00e7\u0131kart art\u0131k, Collins.\u201d<\/p>\n<p style=\"text-align:justify;\">\u201cHay\u0131r.\u201d<\/p>\n<p style=\"text-align:justify;\">\u201cBeni \u00e7\u0131kar ya da sen de gel.\u201d<\/p>\n<p style=\"text-align:justify;\">\u201cHay\u0131r.\u201d<\/p>\n<p style=\"text-align:justify;\">\u201cGel bakal\u0131m biraz nas\u0131l oluyormu\u015f.\u201d<\/p>\n<p style=\"text-align:justify;\">\u201cHay\u0131r. Her an biri gelebilir. Ray.\u201d<\/p>\n<p style=\"text-align:justify;\">\u201cKimse gelmez.\u201d<\/p>\n<p style=\"text-align:justify;\">\u201cGelir. Leggo.\u201d<\/p>\n<p style=\"text-align:justify;\">Uzun bir \u00f6p\u00fc\u015f ve bu \u00f6p\u00fc\u015ften uzak bir tutku ger\u00e7ekle\u015fti aralar\u0131nda. Sonra Ethel yar\u0131da kesip, hemen sandalyesine geri d\u00f6nd\u00fc. Ray \u00f6p\u00fc\u015f\u00fcrken a\u011flamaya ba\u015flam\u0131\u015ft\u0131. Ray\u2019in dudaklar\u0131ndaki titreme, Ethel i\u00e7in bir i\u015faret olmu\u015ftu.<\/p>\n<p style=\"text-align:justify;\">\u201cRay,\u201d dedi Ethel sandalyeden. \u201cRay, bug\u00fcn kimi g\u00f6rd\u00fcm biliyor musun?\u201d Ray\u2019in vermeye \u00e7al\u0131\u015ft\u0131\u011f\u0131 cevap \u015f\u00f6yle oldu: \u201c\u2026 umrumda de\u011fil kimi g\u00f6rd\u00fc\u011f\u00fcn.\u201d<\/p>\n<p style=\"text-align:justify;\">\u201cHelen Masterson.\u201d \u00d6ne do\u011fru e\u011filmi\u015fti Ethel. \u201cK\u0131yafet bakmaya gelmi\u015fti. K\u00fcrklerin i\u00e7inde bo\u011fulmu\u015f gibiydi. Pyhllis kap\u0131dayd\u0131 o geldi\u011finde. Masterson\u2019un direkt Pierce\u2019e gitti\u011fini ve benim i\u00e7in Vogue\u2019daki \u015fu mavi elbiseyi sordu\u011funu s\u00f6yledi\u2014sana g\u00f6stermi\u015ftim hani? Hat\u0131rlad\u0131n m\u0131?\u201d<\/p>\n<p style=\"text-align:justify;\">Ellerini, sa\u00e7lar\u0131n\u0131n aras\u0131ndan sandalyeye s\u0131k\u0131\u015ft\u0131r\u0131yordu Ray, parmaklar\u0131ndaki ac\u0131y\u0131 bu \u015fekilde giderebilece\u011fini d\u00fc\u015f\u00fcnerek.<\/p>\n<p style=\"text-align:justify;\">\u201cOna g\u00f6stermek zorunda kald\u0131m. Bana ilk s\u00f6yledi\u011fi \u015fey ne oldu biliyor musun? Durup dururken. \u2018Ray Nas\u0131l?\u2019 \u0130yi oldu\u011funu s\u00f6yledim. Sonra bana, ne zaman evlenece\u011fimizi sordu. Chicago\u2019dan d\u00f6nd\u00fc\u011f\u00fcn ilk f\u0131rsatta evlenece\u011fimizi s\u00f6yledim.\u201d<\/p>\n<p style=\"text-align:justify;\">Her nefes al\u0131\u015f\u0131nda, alt duda\u011f\u0131 kas\u0131larak, thhhttttt diye bir ses \u00e7\u0131kar\u0131yordu Ray.<\/p>\n<p style=\"text-align:justify;\">\u201cNeden Chicago dedim bilmiyorum, California haricinde d\u00fc\u015f\u00fcnebildi\u011fim en uzak yer oldu, California da fazla uzak olurdu.\u201d<\/p>\n<p style=\"text-align:justify;\">Ray y\u00fcz\u00fcn\u00fcn \u0131slakl\u0131\u011f\u0131n\u0131, yast\u0131\u011f\u0131n k\u00f6\u015fesine siliyordu.<\/p>\n<p style=\"text-align:justify;\">\u201cMavi olan\u0131 ve iki elbiseyi daha ald\u0131. En m\u00fckemmelleriydi.\u201d Ethel kalkt\u0131, pencereye do\u011fru y\u00fcr\u00fcd\u00fc ve s\u0131rt\u0131 Ray\u2019e d\u00f6n\u00fck \u015fekilde dikildi. Thhhttttt sesi devam ediyordu arkas\u0131nda. Nihayet kontrol alt\u0131na al\u0131nm\u0131\u015f gibi sakinledi duda\u011f\u0131n\u0131n sesi, sadece bo\u011faz\u0131ndaki h\u0131r\u0131lt\u0131 duyuluyordu bu kez.<\/p>\n<p style=\"text-align:justify;\">\u201cEthel\u2014\u201c<\/p>\n<p style=\"text-align:justify;\">\u201cEfendim?\u201d\u2014arkas\u0131n\u0131 d\u00f6nmeden.<\/p>\n<p style=\"text-align:justify;\">\u201cGel buraya.\u201d<\/p>\n<p style=\"text-align:justify;\">\u201cBurada iyiyim.\u201d<\/p>\n<p style=\"text-align:justify;\">\u201cHay\u0131r, buraya gel.\u201d<\/p>\n<p style=\"text-align:justify;\">\u201cBurada iyiyim. Duvardaki tu\u011flalar\u0131 say\u0131yorum.\u201d<\/p>\n<p style=\"text-align:justify;\">\u201cEthel. Dinle. Bo\u015falt beni. \u0130htiyac\u0131m var buna. C\u0131v\u0131k c\u0131v\u0131k bir bo\u015falma sadece. Ethel. Allah a\u015fk\u0131na.\u201d<\/p>\n<p style=\"text-align:justify;\">\u201cBir daha bunu yapmayaca\u011f\u0131n\u0131 sanm\u0131\u015ft\u0131m.\u201d<\/p>\n<p style=\"text-align:justify;\">\u201cDinle bir. Tek iste\u011fim bo\u015falmak. Kendimi s\u0131namak istiyorum. Hepsi bu. Ethel. Allah kahretsin, biraz bo\u015falmak beni incitmez. Ethel. O i\u011fren\u00e7 y\u00fcz\u00fcn\u00fc bana \u00e7evir!\u201d<\/p>\n<p style=\"text-align:justify;\">Ona do\u011fru d\u00f6nd\u00fc Ethel. \u201cYapamam Ray. Yapamayaca\u011f\u0131m\u0131 biliyorsun. Neden istiyorsun?\u201d<\/p>\n<p style=\"text-align:justify;\">\u201cYapabilirsin! Yapabilece\u011fini bal gibi biliyorsun. Bo\u015faltabilirsin beni. Tek iste\u011fim bu. Yemin ederim bak. Kendimi s\u0131namam\u0131 istemez misin? Daha iyi olmam\u0131 istemez misin? Bana bak!\u201d<\/p>\n<p style=\"text-align:justify;\">\u201cL\u00fctfen. Yere d\u00fc\u015feceksin bak.\u201d Ethel ona do\u011fru y\u00f6nelince, Ray, onu kolundan yakalay\u0131verdi.<\/p>\n<p style=\"text-align:justify;\">\u201cEthel. A\u015fk\u0131m, l\u00fctfen. \u0130\u011fren\u00e7, c\u0131v\u0131k c\u0131v\u0131k bo\u015falaca\u011f\u0131m sadece. Bak. G\u00fczel bir a\u00e7\u0131 \u00a0yakalad\u0131m burada. Bak, duyacaks\u0131n biri gelirse. Bir bardak koyabilirsin. \u015eu lanet masan\u0131n \u00fczerine koyars\u0131n. Ve kimse fark etmez. Kendimi test edebilirim. Duyuyor musun?\u201d<\/p>\n<p style=\"text-align:justify;\">\u201cDuyuyorum.\u201d<\/p>\n<p style=\"text-align:justify;\">\u201c\u2014Ama \u015fey yapacak m\u0131s\u0131n? \u015eey, yap\u0131can m\u0131? A\u015fk\u0131m?\u201d<\/p>\n<p style=\"text-align:justify;\">\u201cHay\u0131\u0131\u0131\u0131r! L\u00fctfen.\u201d Kolunu ondan kurtarm\u0131\u015ft\u0131 Ethel. Art\u0131k Ray\u2019in elinde bir koz kalmam\u0131\u015ft\u0131. S\u00f6verek, kafas\u0131n\u0131 yast\u0131\u011fa g\u00f6md\u00fc tekrardan, duda\u011f\u0131n\u0131n titremesi zay\u0131flam\u0131\u015f, g\u00f6zleri k\u0131s\u0131lm\u0131\u015ft\u0131. Korkun\u00e7 bir \u015fekilde nefes al\u0131yordu. \u201cPek\u00e2l\u00e2,\u201d dedi Ethel\u2019a, nefes nefese. \u201corospu.\u201d<\/p>\n<p style=\"text-align:justify;\">Ethel pencerenin arkas\u0131ndayd\u0131.<\/p>\n<p style=\"text-align:justify;\">\u201cBeni seviyorsun. Ah, seviyorsun tabii! K\u00f6pek gibi seviyorsun beni, beni seviyorsun. Ne yalanc\u0131 ama. Ne i\u011fren\u00e7 k\u00fc\u00e7\u00fck yalanc\u0131s\u0131n ama sen. Hadi. \u0130kile. Defol git buradan. Hadi. Duydun. Defol git buradan.\u201d<\/p>\n<p style=\"text-align:justify;\">\u0130kisi de kap\u0131da bir t\u0131k\u0131rt\u0131 duydu. Doktor Stone kontrol i\u00e7in gelmi\u015fti.<\/p>\n<p style=\"text-align:justify;\">\u201cPek\u00e2l\u00e2!\u201d dedi Doktor Stone. \u201cNedir bu? Ziyaret\u00e7iler mi?\u201d Ethel\u2019a g\u00fcl\u00fcmsedi.<\/p>\n<p style=\"text-align:justify;\">\u201cTam da \u00e7\u0131k\u0131yordum,\u201d dedi Ethel doktora. Phyllis\u2019in kitab\u0131n\u0131 alarak ilerledi, \u00e7\u0131karken ete\u011fini d\u00fczeltiyordu.<\/p>\n<p style=\"text-align:justify;\">\u201c\u00dc\u015fengecimiz nas\u0131l bakal\u0131m bug\u00fcn?\u201d diye sordu Doktor Stone. \u201cNas\u0131l hissediyorsun evlat?\u201d Cevap olarak \u00f6b\u00fcr tarafa d\u00f6nd\u00fc Ray. \u201cYar\u0131n yine gelece\u011fim, Ray,\u201d dedi Ethel.<\/p>\n<p style=\"text-align:justify;\">Ray\u2019in y\u00fcz\u00fcn\u00fcn \u00e7o\u011fu yast\u0131ktayd\u0131. \u201cE\u011fer bir daha buraya gelirsen seni \u00f6ld\u00fcr\u00fcr\u00fcm. Def ol.\u201d<\/p>\n<p style=\"text-align:justify;\">\u201cHey!\u201d dedi Doktor Stone. \u201cHey, dur bakal\u0131m! Dur, Bessie\u201d<\/p>\n<p style=\"text-align:justify;\">Doktor Stone iki tarafl\u0131 kap\u0131ya bast\u0131rarak \u00e7\u0131kt\u0131 ve Ethel\u2019in yan\u0131ndan, koridor boyunca ilerledi.<\/p>\n<p style=\"text-align:justify;\">\u201cMuhtemelen bu \u00f6\u011flenden sonra b\u00f6bre\u011fini y\u0131kayaca\u011f\u0131z Ray\u2019in,\u201d dedi Doktor Stone.<\/p>\n<p style=\"text-align:justify;\">\u201cEvet,\u201d dedi Ethel.<\/p>\n<p style=\"text-align:justify;\">\u201c\u0130nsan v\u00fccudu, makine gibi, bilirsin. Temiz tutmak gerekiyor.\u201d<\/p>\n<p style=\"text-align:justify;\">\u201cEvet,\u201d diye tekrar etti Ethel.<\/p>\n<p style=\"text-align:justify;\">\u201cDoktor Stone\u2019un burnu hafif\u00e7e, k\u00fc\u00e7\u00fcmseyici bir ses \u00e7\u0131kard\u0131, genzinde bir engel varm\u0131\u015f gibiydi.<\/p>\n<p style=\"text-align:justify;\">\u201cBug\u00fcn onun do\u011fum g\u00fcn\u00fc,\u201d dedi Ethel.<\/p>\n<p style=\"text-align:justify;\">\u201cNe g\u00fczel!\u201d dedi Doktor Stone. \u201cBilmiyordum bak!\u201d<\/p>\n<p style=\"text-align:justify;\">\u201cYirmi iki ya\u015f\u0131na girdi.\u201d<\/p>\n<p style=\"text-align:justify;\">Derken asans\u00f6r geldi, i\u00e7erisi kalabal\u0131kt\u0131, Bu y\u00fczden Ethel\u2019in aceleyle asans\u00f6re binmekten ba\u015fka \u015fans\u0131 yoktu.<\/p>\n<p style=\"text-align:justify;\">\u201cG\u00f6r\u00fc\u015f\u00fcr\u00fcz,\u201d dedi Ethel.<\/p>\n<p style=\"text-align:justify;\">\u201cG\u00f6r\u00fc\u015f\u00fcr\u00fcz!\u201d dedi Doktor Stone, kelebek g\u00f6zl\u00fc\u011f\u00fcn\u00fc ald\u0131 burnundan. Asans\u00f6r a\u015fa\u011f\u0131ya do\u011fru indi, t\u00fcm rutubetli alanlarda Ethel\u2019i titreterek.<\/p>\n<p style=\"text-align:right;\"><em>M\u00fctercim: L.<\/em><\/p>\n<p><img loading=\"lazy\" data-attachment-id=\"2390\" data-permalink=\"https:\/\/kvlrap.wordpress.com\/2020\/10\/05\/birthday-boy-jerome-david-salinger\/hamza-2\/\" data-orig-file=\"https:\/\/kvlrap.files.wordpress.com\/2020\/04\/hamza-1.jpg\" data-orig-size=\"540,360\" data-comments-opened=\"1\" data-image-meta=\"{&quot;aperture&quot;:&quot;3.2&quot;,&quot;credit&quot;:&quot;&quot;,&quot;camera&quot;:&quot;Canon EOS-1Ds Mark II&quot;,&quot;caption&quot;:&quot;&quot;,&quot;created_timestamp&quot;:&quot;1210824180&quot;,&quot;copyright&quot;:&quot;&quot;,&quot;focal_length&quot;:&quot;35&quot;,&quot;iso&quot;:&quot;3200&quot;,&quot;shutter_speed&quot;:&quot;0.05&quot;,&quot;title&quot;:&quot;&quot;,&quot;orientation&quot;:&quot;1&quot;}\" data-image-title=\"Hamza\" data-image-description=\"\" data-medium-file=\"https:\/\/kvlrap.files.wordpress.com\/2020\/04\/hamza-1.jpg?w=300\" data-large-file=\"https:\/\/kvlrap.files.wordpress.com\/2020\/04\/hamza-1.jpg?w=540\" class=\"alignnone  wp-image-2390\" src=\"https:\/\/kvlrap.files.wordpress.com\/2020\/04\/hamza-1.jpg?w=704&#038;h=469\" alt=\"Hamza\" width=\"704\" height=\"469\" srcset=\"https:\/\/kvlrap.files.wordpress.com\/2020\/04\/hamza-1.jpg 540w, https:\/\/kvlrap.files.wordpress.com\/2020\/04\/hamza-1.jpg?w=150&amp;h=100 150w, https:\/\/kvlrap.files.wordpress.com\/2020\/04\/hamza-1.jpg?w=300&amp;h=200 300w\" sizes=\"(max-width: 704px) 100vw, 704px\" \/><\/p>"},"thr:total":"0","comments":{"commentCount":null,"comments":[]}}